{
   "geocoded_waypoints" : [
      {
         "geocoder_status" : "OK",
         "place_id" : "ChIJ_9uVvrtLd0gRFLcjVccEo2g",
         "types" : [ "premise" ]
      },
      {
         "geocoder_status" : "OK",
         "place_id" : "ChIJO398h_YtY0gRY2NjmxKPX40",
         "types" : [ "street_address" ]
      }
   ],
   "routes" : [
      {
         "bounds" : {
            "northeast" : {
               "lat" : 54.66824940000001,
               "lng" : -1.4990683
            },
            "southwest" : {
               "lat" : 52.4074841,
               "lng" : -3.5521997
            }
         },
         "copyrights" : "Map data ©2019 Google",
         "legs" : [
            {
               "distance" : {
                  "text" : "379 km",
                  "value" : 378821
               },
               "duration" : {
                  "text" : "4 hours 15 mins",
                  "value" : 15291
               },
               "end_address" : "13 Rowntree Cres, Moresby Parks, Whitehaven CA28 8XE, UK",
               "end_location" : {
                  "lat" : 54.5597613,
                  "lng" : -3.5521997
               },
               "start_address" : "Dewis Lodge, Coventry CV1 5EP, UK",
               "start_location" : {
                  "lat" : 52.408632,
                  "lng" : -1.50819
               },
               "steps" : [
                  {
                     "distance" : {
                        "text" : "90 m",
                        "value" : 90
                     },
                     "duration" : {
                        "text" : "1 min",
                        "value" : 32
                     },
                     "end_location" : {
                        "lat" : 52.4078441,
                        "lng" : -1.5084445
                     },
                     "html_instructions" : "Head \u003cb\u003esouth\u003c/b\u003e on \u003cb\u003eCuckoo Ln\u003c/b\u003e toward \u003cb\u003eSt Michael's Ave\u003c/b\u003e",
                     "polyline" : {
                        "points" : "}`{~HdqeHfAh@B@pAD"
                     },
                     "start_location" : {
                        "lat" : 52.408632,
                        "lng" : -1.50819
                     },
                     "travel_mode" : "DRIVING"
                  },
                  {
                     "distance" : {
                        "text" : "0.2 km",
                        "value" : 203
                     },
                     "duration" : {
                        "text" : "1 min",
                        "value" : 69
                     },
                     "end_location" : {
                        "lat" : 52.406872,
                        "lng" : -1.5066065
                     },
                     "html_instructions" : "Turn \u003cb\u003eleft\u003c/b\u003e onto \u003cb\u003eBayley Ln\u003c/b\u003e",
                     "maneuver" : "turn-left",
                     "polyline" : {
                        "points" : "_|z~HvreHAo@Ba@?EBEBIBWFoB?g@@I@IFMHIHGJGJEPEx@QFADAB@D@NB"
                     },
                     "start_location" : {
                        "lat" : 52.4078441,
                        "lng" : -1.5084445
                     },
                     "travel_mode" : "DRIVING"
                  },
                  {
                     "distance" : {
                        "text" : "0.2 km",
                        "value" : 166
                     },
                     "duration" : {
                        "text" : "1 min",
                        "value" : 34
                     },
                     "end_location" : {
                        "lat" : 52.4067844,
                        "lng" : -1.5041669
                     },
                     "html_instructions" : "Turn \u003cb\u003eleft\u003c/b\u003e onto \u003cb\u003eJordan Well\u003c/b\u003e/\u003cb\u003eB4544\u003c/b\u003e",
                     "maneuver" : "turn-left",
                     "polyline" : {
                        "points" : "}uz~HhgeH?s@?M?[LcHBy@?k@"
                     },
                     "start_location" : {
                        "lat" : 52.406872,
                        "lng" : -1.5066065
                     },
                     "travel_mode" : "DRIVING"
                  },
                  {
                     "distance" : {
                        "text" : "0.3 km",
                        "value" : 345
                     },
                     "duration" : {
                        "text" : "1 min",
                        "value" : 59
                     },
                     "end_location" : {
                        "lat" : 52.4070414,
                        "lng" : -1.499195
                     },
                     "html_instructions" : "Continue onto \u003cb\u003eGosford St\u003c/b\u003e",
                     "polyline" : {
                        "points" : "kuz~H`xdH@qBPsDB]@a@@Q?Q?O?IAo@?U?[?CAO[aEIiAI_@CUEm@Ec@Ku@"
                     },
                     "start_location" : {
                        "lat" : 52.4067844,
                        "lng" : -1.5041669
                     },
                     "travel_mode" : "DRIVING"
                  },
                  {
                     "distance" : {
                        "text" : "50 m",
                        "value" : 50
                     },
                     "duration" : {
                        "text" : "1 min",
                        "value" : 11
                     },
                     "end_location" : {
                        "lat" : 52.4074797,
                        "lng" : -1.4990626
                     },
                     "html_instructions" : "At the roundabout, take the \u003cb\u003e1st\u003c/b\u003e exit and stay on \u003cb\u003eGosford St\u003c/b\u003e",
                     "maneuver" : "roundabout-left",
                     "polyline" : {
                        "points" : "_wz~H|xcHA??AM@EAMCs@S"
                     },
                     "start_location" : {
                        "lat" : 52.4070414,
                        "lng" : -1.499195
                     },
                     "travel_mode" : "DRIVING"
                  },
                  {
                     "distance" : {
                        "text" : "93 m",
                        "value" : 93
                     },
                     "duration" : {
                        "text" : "1 min",
                        "value" : 13
                     },
                     "end_location" : {
                        "lat" : 52.4078039,
                        "lng" : -1.5003108
                     },
                     "html_instructions" : "At the roundabout, take the \u003cb\u003e1st\u003c/b\u003e exit onto the \u003cb\u003eRingway Whitefriars\u003c/b\u003e/\u003cb\u003eA4053\u003c/b\u003e ramp to \u003cb\u003eRing Road\u003c/b\u003e",
                     "maneuver" : "roundabout-left",
                     "polyline" : {
                        "points" : "wyz~HbxcH?@A??@A??@A@A@CNENQ|AO|@Kr@"
                     },
                     "start_location" : {
                        "lat" : 52.4074797,
                        "lng" : -1.4990626
                     },
                     "travel_mode" : "DRIVING"
                  },
                  {
                     "distance" : {
                        "text" : "0.8 km",
                        "value" : 826
                     },
                     "duration" : {
                        "text" : "1 min",
                        "value" : 68
                     },
                     "end_location" : {
                        "lat" : 52.41278860000001,
                        "lng" : -1.5089156
                     },
                     "html_instructions" : "Keep \u003cb\u003eright\u003c/b\u003e at the fork, follow signs for \u003cb\u003eA45\u003c/b\u003e/\u003cb\u003eRing Road\u003c/b\u003e/\u003cb\u003eBirmingham\u003c/b\u003e and merge onto \u003cb\u003eRingway Whitefriars\u003c/b\u003e/\u003cb\u003eA4053\u003c/b\u003e\u003cdiv style=\"font-size:0.9em\"\u003eContinue to follow A4053\u003c/div\u003e",
                     "maneuver" : "fork-right",
                     "polyline" : {
                        "points" : "w{z~H|_dHKZGTGf@S~AIr@M|@EVMb@GRGNKRILQTKJMJa@Vc@VKDYRQLCBONGFIHIHILW^SZMPIJKHQDMXMVUb@KTMXu@`BMVGNq@xAq@xAo@tAEH_@z@]r@Wn@q@tA}@nBUj@EHCFCHAJ"
                     },
                     "start_location" : {
                        "lat" : 52.4078039,
                        "lng" : -1.5003108
                     },
                     "travel_mode" : "DRIVING"
                  },
                  {
                     "distance" : {
                        "text" : "0.6 km",
                        "value" : 623
                     },
                     "duration" : {
                        "text" : "1 min",
                        "value" : 48
                     },
                     "end_location" : {
                        "lat" : 52.4106216,
                        "lng" : -1.5171852
                     },
                     "html_instructions" : "At the roundabout, take the \u003cb\u003e1st\u003c/b\u003e exit onto \u003cb\u003eRingway St Nicholas\u003c/b\u003e/\u003cb\u003eA4053\u003c/b\u003e\u003cdiv style=\"font-size:0.9em\"\u003eContinue to follow A4053\u003c/div\u003e",
                     "maneuver" : "roundabout-left",
                     "polyline" : {
                        "points" : "}z{~HvueH?@?@?@?@?DAF?DADAFADAF?DAD?P?R?f@Dd@Db@Ff@PfA`@lC`@dCV`BVhBp@fEX`BDXDNF^Jb@Hb@DNLj@ZhALb@N`@L`@Rj@Tj@N\\R`@BF"
                     },
                     "start_location" : {
                        "lat" : 52.41278860000001,
                        "lng" : -1.5089156
                     },
                     "travel_mode" : "DRIVING"
                  },
                  {
                     "distance" : {
                        "text" : "0.1 km",
                        "value" : 145
                     },
                     "duration" : {
                        "text" : "1 min",
                        "value" : 15
                     },
                     "end_location" : {
                        "lat" : 52.4095473,
                        "lng" : -1.5183468
                     },
                     "html_instructions" : "Take the \u003cb\u003eA4114\u003c/b\u003e ramp to \u003cb\u003eA45\u003c/b\u003e/\u003cb\u003eBirmingham\u003c/b\u003e/\u003cb\u003eCoundon\u003c/b\u003e/\u003cb\u003eAllesley\u003c/b\u003e",
                     "polyline" : {
                        "points" : "km{~HligHJBDBFDNVDDJPNXJNFHJJFJNJLLf@^LJLV"
                     },
                     "start_location" : {
                        "lat" : 52.4106216,
                        "lng" : -1.5171852
                     },
                     "travel_mode" : "DRIVING"
                  },
                  {
                     "distance" : {
                        "text" : "0.7 km",
                        "value" : 679
                     },
                     "duration" : {
                        "text" : "1 min",
                        "value" : 76
                     },
                     "end_location" : {
                        "lat" : 52.4121359,
                        "lng" : -1.5269211
                     },
                     "html_instructions" : "At the roundabout, take the \u003cb\u003e2nd\u003c/b\u003e exit onto \u003cb\u003eHolyhead Rd\u003c/b\u003e/\u003cb\u003eA4114\u003c/b\u003e",
                     "maneuver" : "roundabout-left",
                     "polyline" : {
                        "points" : "uf{~HtpgHHDBDBFDHBP?R?TANALEJCHEDEFKHE@MDIFEBCBA@EHGTADCFUjAQfA_@rBMr@QdAq@nC]xA_@bBCJ}@fDK`@q@nCCHkAvEI^E\\ARALAjA"
                     },
                     "start_location" : {
                        "lat" : 52.4095473,
                        "lng" : -1.5183468
                     },
                     "travel_mode" : "DRIVING"
                  },
                  {
                     "distance" : {
                        "text" : "2.2 km",
                        "value" : 2155
                     },
                     "duration" : {
                        "text" : "4 mins",
                        "value" : 242
                     },
                     "end_location" : {
                        "lat" : 52.4206138,
                        "lng" : -1.5547965
                     },
                     "html_instructions" : "At the roundabout, take the \u003cb\u003e2nd\u003c/b\u003e exit and stay on \u003cb\u003eHolyhead Rd\u003c/b\u003e/\u003cb\u003eA4114\u003c/b\u003e",
                     "maneuver" : "roundabout-left",
                     "polyline" : {
                        "points" : "{v{~HffiH@@@?@@?@@?@@@@?@@@?@@@?@@@?B?@@@?@?B?@?B?@?@?B?@?@?B?@AB?@AB?@A@?@A@A@?@A?A@?@A?A@A?A??@A?A?A?A?AAA?AAA?AAAAAAi@p@INILCFMZUdAERMj@EROt@?XGRk@xBcAfEIXy@dDGZQj@IXENYp@ABAFSp@WlAOl@]pASx@Od@K\\EJERa@vAk@tBo@xBCNOf@WbASx@Op@Qx@Kb@WtAKj@o@nDUlASpAYjBCN?DQ`Aa@rCa@nCETAHIf@ObAgA~HEVUpAa@zCObAQ`AQdAg@|Ca@`Cg@xCUnAYzA[xA[tAu@xC]pAaBrG]rA?\\@THp@"
                     },
                     "start_location" : {
                        "lat" : 52.4121359,
                        "lng" : -1.5269211
                     },
                     "travel_mode" : "DRIVING"
                  },
                  {
                     "distance" : {
                        "text" : "1.1 km",
                        "value" : 1056
                     },
                     "duration" : {
                        "text" : "1 min",
                        "value" : 68
                     },
                     "end_location" : {
                        "lat" : 52.4218041,
                        "lng" : -1.5691796
                     },
                     "html_instructions" : "At the roundabout, take the \u003cb\u003e2nd\u003c/b\u003e exit onto \u003cb\u003ePickford Way\u003c/b\u003e/\u003cb\u003eA4114\u003c/b\u003e",
                     "maneuver" : "roundabout-left",
                     "polyline" : {
                        "points" : "yk}~HntnHD@LHFHHJNRBNFTBPDh@APCPEXGRGRGHMn@Y|@e@rAQh@Ql@_@~A_@tBYzBMlASbBQ|ASfBW|BQfBMhAQdBMfBGlACn@Cv@Ar@Av@?bB?rADbBFpAFhALbBJhAFx@Ff@B^BNFRHNNR"
                     },
                     "start_location" : {
                        "lat" : 52.4206138,
                        "lng" : -1.5547965
                     },
                     "travel_mode" : "DRIVING"
                  },
                  {
                     "distance" : {
                        "text" : "0.2 km",
                        "value" : 226
                     },
                     "duration" : {
                        "text" : "1 min",
                        "value" : 22
                     },
                     "end_location" : {
                        "lat" : 52.4224892,
                        "lng" : -1.5710148
                     },
                     "html_instructions" : "At the roundabout, take the \u003cb\u003e3rd\u003c/b\u003e exit",
                     "maneuver" : "roundabout-left",
                     "polyline" : {
                        "points" : "gs}~HjnqHFHDDNVL^DJDPDZ@VAf@Ah@ETEPK`@?@A@A@AB?@A@A@A@GJGFMFQFUDI?KAOEA?AAA?AAA?AAA?AAe@J"
                     },
                     "start_location" : {
                        "lat" : 52.4218041,
                        "lng" : -1.5691796
                     },
                     "travel_mode" : "DRIVING"
                  },
                  {
                     "distance" : {
                        "text" : "0.3 km",
                        "value" : 302
                     },
                     "duration" : {
                        "text" : "1 min",
                        "value" : 19
                     },
                     "end_location" : {
                        "lat" : 52.4250275,
                        "lng" : -1.5724974
                     },
                     "html_instructions" : "Take the ramp on the \u003cb\u003eright\u003c/b\u003e to \u003cb\u003eMeriden\u003c/b\u003e/\u003cb\u003eBirmingham Airport\u003c/b\u003e/\u003cb\u003eN.E.C.\u003c/b\u003e",
                     "polyline" : {
                        "points" : "qw}~HxyqHq@RG@}@V}@Z}@`@}@d@k@^s@h@a@\\MLe@b@SA"
                     },
                     "start_location" : {
                        "lat" : 52.4224892,
                        "lng" : -1.5710148
                     },
                     "travel_mode" : "DRIVING"
                  },
                  {
                     "distance" : {
                        "text" : "9.3 km",
                        "value" : 9325
                     },
                     "duration" : {
                        "text" : "6 mins",
                        "value" : 381
                     },
                     "end_location" : {
                        "lat" : 52.4455058,
                        "lng" : -1.7027557
                     },
                     "html_instructions" : "Merge onto \u003cb\u003eBirmingham Rd\u003c/b\u003e/\u003cb\u003eA45\u003c/b\u003e\u003cdiv style=\"font-size:0.9em\"\u003eContinue to follow A45\u003c/div\u003e",
                     "maneuver" : "merge",
                     "polyline" : {
                        "points" : "mg~~HbcrHIJk@r@[`@EHa@j@ED_AtA{@rAYb@o@bAm@hAUf@GLy@`Cc@`BSfAY~AShAIn@Ip@OlA]jDYvCYvCQdBKdAOlAWxBABKn@Kn@q@~Dy@vEk@hDg@lCy@vE[`BSdAOp@i@dC_@zAu@`Du@~COl@CNYnAY~AEXUxAYdBq@bEc@jCcArF]bBq@|CKj@eBlHUbA}@vDcBnHuA|FsAzFa@bBkA~E}@xDk@fCaAfEu@bDk@jCq@fDYxA[dBa@xB_@xB[vBMv@[tBIn@UbBWnB]xCa@nDKhA]vDMtAUzCQvBQjCGlAObCU|DMzBEj@Ej@k@|J]jGYjFY~EG`AWxEUtDQ|CQxCSxDUvDGv@Y`FYhFOhCo@tK]jGOzCIfBQtEIzBGpAOpCc@|M_@bLU`HG|AObESdGUzGEnAEdBMlFUjJOjGE~BElAE~AEtAEbAEz@IhBIhAOrBIfAUjCIp@MjAIt@MfAS`Be@jEc@~DQhBCTE^ObBCRc@jFWxCg@nGMvAG~@Gp@GjAGbAEz@OdFChB?VAnC?jA@x@BfA@hABx@DnAFlAD~@F~@FlAHhADt@FjADt@Dt@DlABn@Bp@@v@DpA@pA@h@?`A@dBAtBCfBAn@AdAExAEv@Cp@KbCKzCGrAAj@C~@An@A^A~@?dAAzABrADtCTlM@pABnA@f@@lAD`B@z@DnABdADzA@v@"
                     },
                     "start_location" : {
                        "lat" : 52.4250275,
                        "lng" : -1.5724974
                     },
                     "travel_mode" : "DRIVING"
                  },
                  {
                     "distance" : {
                        "text" : "0.4 km",
                        "value" : 374
                     },
                     "duration" : {
                        "text" : "1 min",
                        "value" : 34
                     },
                     "end_location" : {
                        "lat" : 52.4448146,
                        "lng" : -1.7080847
                     },
                     "html_instructions" : "Take the \u003cb\u003eM42\u003c/b\u003e ramp to \u003cb\u003eSolihull\u003c/b\u003e/\u003cb\u003eLichfield\u003c/b\u003e/\u003cb\u003eM5\u003c/b\u003e/\u003cb\u003eM40\u003c/b\u003e/\u003cb\u003eM6\u003c/b\u003e/\u003cb\u003eM1\u003c/b\u003e",
                     "polyline" : {
                        "points" : "mgb_IfqkIP`ADt@Dl@HrAHhBNdDFlCH|CDpADn@DZFXDNBFR`@"
                     },
                     "start_location" : {
                        "lat" : 52.4455058,
                        "lng" : -1.7027557
                     },
                     "travel_mode" : "DRIVING"
                  },
                  {
                     "distance" : {
                        "text" : "0.9 km",
                        "value" : 892
                     },
                     "duration" : {
                        "text" : "2 mins",
                        "value" : 90
                     },
                     "end_location" : {
                        "lat" : 52.4493795,
                        "lng" : -1.7088928
                     },
                     "html_instructions" : "At \u003cb\u003eBickenhill Interchange\u003c/b\u003e, take the \u003cb\u003e5th\u003c/b\u003e exit onto the \u003cb\u003eM42\u003c/b\u003e ramp to \u003cb\u003eM1\u003c/b\u003e/\u003cb\u003eM6\u003c/b\u003e/\u003cb\u003eLondon\u003c/b\u003e/\u003cb\u003eLichfield\u003c/b\u003e/\u003cb\u003eTamworth\u003c/b\u003e",
                     "maneuver" : "roundabout-left",
                     "polyline" : {
                        "points" : "acb_InrlIp@p@JJv@~AZjAJf@JrA@f@AZCl@Gj@I\\EVa@dAc@h@c@T[JYDS?[C{@[EEg@o@]i@c@}@GS[M]o@[i@UY[[OKOIk@SmA]aASwAYw@K]Eu@Kc@ESM[W"
                     },
                     "start_location" : {
                        "lat" : 52.4448146,
                        "lng" : -1.7080847
                     },
                     "travel_mode" : "DRIVING"
                  },
                  {
                     "distance" : {
                        "text" : "8.7 km",
                        "value" : 8732
                     },
                     "duration" : {
                        "text" : "5 mins",
                        "value" : 327
                     },
                     "end_location" : {
                        "lat" : 52.52587699999999,
                        "lng" : -1.7290383
                     },
                     "html_instructions" : "Merge onto \u003cb\u003eM42\u003c/b\u003e",
                     "maneuver" : "merge",
                     "polyline" : {
                        "points" : "s_c_IpwlIk@A}AAi@@[?}@BW@{AHO?w@Ho@F}@JkARe@Jm@Jy@P[HYFWFq@NyCr@cAR{@NkB\\{@LgAN_BPmAH{AJ{ADcAB]?eA?wAAy@Cq@C}@CqAImAGu@GoBO}AK_AGaCMgAEiAE{@As@?q@?aA@mABs@B[B]@_AFo@D[BcAJeALaAL]FaANgAPeAPy@PC@q@Lm@Lg@Js@Lg@J_@Fs@J_AJa@DUDS@o@Dy@Fq@Bw@B_A?gA?_AEUAeAEa@CWC_@E[Cm@Im@Iq@I}@OkASw@Mu@OSCmBWoBYuBUeFYmAE{@?{@A_@?qAB}@Do@Fa@FOBQBSD_@JiAZ_A\\UJu@^g@ZmAt@kAx@c@\\gBpAqChBMH{Av@kAh@m@X{@XqA`@e@N_Dx@yA`@uEtAgAXEBaCn@mCt@kH`CiFfB}FzBqAh@_EdBaAf@c@R{@b@MH_@P]P]Rk@Z]Pk@Z_@Ry@d@OH[Pk@^]RSLWPmExCYPaCbBy@j@eBjAeAt@k@`@[TMJ[TYR]VOJMJMJMHMJQLu@h@]T]V[TOJ]R]R]R]RQHKFOHMFOHMFOFOHMD]POFOFODOF}@ZOFe@Lg@Nk@N_ARo@JkARs@J_@Fo@FQBoAJO?O@_@@K@S?s@@}A?sBCcCGsAC}DKe@?}@@mBDgCLcAJSBa@D_@Dm@J_BTcC`@o@Po@NsCt@aIpBaAT_AV[HYHuPfEeCl@qAZ"
                     },
                     "start_location" : {
                        "lat" : 52.4493795,
                        "lng" : -1.7088928
                     },
                     "travel_mode" : "DRIVING"
                  },
                  {
                     "distance" : {
                        "text" : "0.4 km",
                        "value" : 375
                     },
                     "duration" : {
                        "text" : "1 min",
                        "value" : 14
                     },
                     "end_location" : {
                        "lat" : 52.52922350000001,
                        "lng" : -1.7296597
                     },
                     "html_instructions" : "Keep \u003cb\u003eright\u003c/b\u003e at the fork to continue on \u003cb\u003eM6 Toll\u003c/b\u003e",
                     "maneuver" : "fork-right",
                     "polyline" : {
                        "points" : "w}q_InupIoG~@uAPcHh@Q?"
                     },
                     "start_location" : {
                        "lat" : 52.52587699999999,
                        "lng" : -1.7290383
                     },
                     "travel_mode" : "DRIVING"
                  },
                  {
                     "distance" : {
                        "text" : "33.4 km",
                        "value" : 33363
                     },
                     "duration" : {
                        "text" : "19 mins",
                        "value" : 1120
                     },
                     "end_location" : {
                        "lat" : 52.668364,
                        "lng" : -2.072026
                     },
                     "html_instructions" : "Keep \u003cb\u003eright\u003c/b\u003e at the fork to stay on \u003cb\u003eM6 Toll\u003c/b\u003e\u003cdiv style=\"font-size:0.9em\"\u003eToll road\u003c/div\u003e",
                     "maneuver" : "fork-right",
                     "polyline" : {
                        "points" : "srr_IjypIkELeCDiC?qFAkNA}AAqJAaDEsBAsHEO?qA?Q?i@?y@AyGAO?y@@kA?iADs@D}@H{@Ns@Lk@PKFcAXq@Ts@Xw@\\{@d@{@h@{@j@{@n@eA`Aw@t@u@x@w@`A{@nA_AvAy@xAaAjBaAtBw@nBu@lBkA|CyBjGUj@}AnE}ApEwB`GqAtD]~@a@dASh@kBzEi@lAuBtEQ^kDvGmB`DsEnHeBnCoApBgAfBsA~Bs@pAu@rAy@~Au@~Aq@vAMX[r@Q`@MZa@bAi@lAKVIRWn@k@~A_@`AQh@Sj@[|@Qh@IX]fA[dAe@~AQp@YdAGT_@pA_AzDa@dB_@`Be@tB]zA_@`BUfA]|A]zA]xAi@zBs@dCo@pBo@hBq@fBu@dB[l@MXQZ[l@Yj@OVS\\w@pAu@fAk@v@a@h@e@h@e@d@k@n@q@n@YTOL[Xk@b@a@Z[VmAx@o@^k@Zi@X[N]N]N_@Na@N_@Jw@Zo@Ru@Vy@VeA\\iA`@{An@m@ZuAv@s@d@iAz@_@Ze@`@i@d@EBWVSTWVi@l@aAlAo@~@q@dAQVKRWd@o@nAo@rAi@nAYt@KZKT]~@c@tAa@pAa@tA[jAa@zAg@nBo@bCWz@[hAUv@Ol@Sn@Of@m@dBu@rBu@bBs@xAi@bAi@|@s@fAw@hAm@v@mAvAy@x@s@p@eBxAiDfCoAz@iBjAiBdAcAn@}@d@_Ad@uAp@oD`BgC`AsDtAoBl@yA`@m@N]J]HkAZuBd@cC`@wB\\gBV}BV{BRsDTuADsCFS@E?_@?gC@}CE_DKyCOsCW_BSC?g@Ew@GcBOmBMKAK?oBGiC?mAD_ABgBLoBTgAPqATsBd@eBf@aBj@cBp@qBz@YLwCtAsB~@q@X}@Zw@Zc@NOD_@L}@Vs@PeAToAVgC^gBPcBRiALwCZgH`AsBXcC`@uB^yBb@cI|AeCh@sBb@oAXyFxAaAVsA^oA\\]Jo@Pc@NcD`AYJC@_@La@NiA\\cA^kAb@y@Z{@^i@Vs@Zo@\\e@Vq@b@c@Te@Z[To@b@eAv@{@p@kA`Am@f@}AzACBy@|@_A~@aAhAcApA[`@_AnAk@x@uAvBuA|BcAhBa@v@m@jAg@bAYn@Q\\IPy@hBo@|Ag@nA{@vBe@nA]|@{@|BoAlDe@lAm@dBe@rA]bAqA`Eu@bC_AzCk@nBoAdEq@fCs@lCo@bCc@dBKb@Md@Kf@q@nC{@vDQv@a@hBq@`Dy@zD]`Bm@xCm@~Cu@xD[|AMj@s@dDWnAgC~KgBpHiArEq@fC{@dD_AfDe@`BW~@y@zCc@fBQn@iAzEc@vBi@lC_@pBq@vDe@xCc@`D]jCa@lDMpAK|@I|@YnDWrDSzCGdAKdCS`FMxECjBE|CC`C?j@AvA?pA@|B@hCDzDDxBBjAHbCFjBFzALtCT|DZhELdBLvAZlDp@dGb@hDVdBd@~Cl@jDx@tE`@vBl@dDr@dEVzAPlAZzBHp@PbBTrBP~BNvBPxDDfADtBBvC@fB?tAAt@C~BAbAErAEzAEv@GnAE|@OtBQxBGn@OxAOjAS~AEZ]xBY~A[`B[zAm@fC[dAi@nBm@hBo@jBgAjCkAhCyAtCsBzD{BrEkAhCi@lA_BzDeAnC{@|B{@`CsA`EoA~DgAvDkAfEg@rB_AzDw@fD_AtEo@hDg@nCa@xBe@tCa@pCa@tCYxB[|B]tCAN]jDGf@_@tD_@~E]nEO`CO`CQ|CMxCIbCIxBCnBAp@Ah@A~@?lA@bC@bBB`B@n@HbCNbDN`CJlADh@Dh@N`BRdBX|Bj@hEv@pFRzAZxBZrCTzBL`BNzBJ`CDfADnADfBB`B@jBAzCEpDIvCQnDStC[pDUtBUbBe@dDi@bDe@nC_@tBu@vEi@|Da@fD[`DYrDUnDMhCKxCEnACdCA~@CvC?dC@dB@pADtBF~CFvBHfCZzHRtGD|CJxEDjF?vB?vBCxCCdCCzBG~BKhDIrBOvDUzDK`Ba@dFS|Bg@dFg@|D[~BcAhHm@fE]vBMt@k@pDsAxHEXeA~F_AzEeApFOr@Y`B]jBQfAGf@[rBQnAEV]bC_ArEi@nCSz@e@dBc@zAmBfGgCpIUp@kAnDOd@kBxGu@lCi@pBg@lBq@~Cm@dD[tB_@lCUpBUlCIz@Q`CQxCIdCI|CC~CA`D@dCB~ADvADlBHhBLnBBh@NrBNnBB^TjCb@~ERbCV~CJzAPbCDt@VhELpCNdDLzDHpCDvBHpFDxD@tCB~BBlEB`BB|BFlBBdAHlBFzAPnCLpAFz@VxBNnAZzBV~AZbBZ|Ah@|BVdAl@tBb@xAr@pBbCrGj@vA^fA`AdCXz@~@tC\\bA^lA\\nA`@~AZpAb@dB`@fBZzA`@`BRjAb@hCVnBRrBZ|DJ~AHlBDjABvA?tA?rA?pACvBCzAGdBEv@IrAIfAI`AIz@K|@Ix@In@Kv@QdAOx@S`AOv@Ol@Kf@Ol@k@|Bc@xA[bAa@dA[x@m@vAw@~A{BfEiBhDQ^IR"
                     },
                     "start_location" : {
                        "lat" : 52.52922350000001,
                        "lng" : -1.7296597
                     },
                     "travel_mode" : "DRIVING"
                  },
                  {
                     "distance" : {
                        "text" : "148 km",
                        "value" : 148287
                     },
                     "duration" : {
                        "text" : "1 hour 37 mins",
                        "value" : 5832
                     },
                     "end_location" : {
                        "lat" : 53.80444499999999,
                        "lng" : -2.6953854
                     },
                     "html_instructions" : "Continue onto \u003cb\u003eM6\u003c/b\u003e",
                     "polyline" : {
                        "points" : "gxm`IdusK[j@gAxB}CpGEJmBhE[l@eAbC_AbC[l@_@v@gAzBuA`DqBvEuAdD[v@g@nAYr@}E|K{A~CWj@Yl@iAdCiEdJQ`@EHYj@_I|PmDrHyBzE{A`DcBfDy@~AqA|BaBnCyClEoBjCgAtAoAzAs@x@YXWXqArAmAlAg@b@mAfA_At@uAfAu@j@u@j@q@b@o@`@{@h@u@b@iAn@{@b@iAh@y@`@eA`@y@ZmAf@s@TeAZm@P_AXy@PqAZk@HmARy@HgAJcAFoADk@Aw@?c@Aw@Aq@Eq@Eg@GWCy@Mo@IaAQoAYwA_@gA_@cA_@wCcA_FcBoE}AgC_AuCaAkDmA_DiAu@Wu@SECm@S{@Wk@OcAUk@Mw@Mw@KcAK}@IiAG}@CcAA_A?kABu@Dc@Be@B{@HsALwARqBRuBTgCXmBRkD^sCZaBPaAH{@Fy@D_AB}@Bo@BiAA_AAeAC{@CcAE_AIcAKy@I_AMgAQoAWwA[eAUiCo@eCm@g@K{EkAmEcAkFqAkD{@}Cu@mCk@sDo@aAMWEg@GsBUsAKuAIcAEsAEcAAa@AwAAmCDc@@W?y@BiAFaCNyD^mDZuEb@}Eb@yD^_Fd@sCVcBNmDZmBPwANgCTgIv@kHn@o@HkJz@ePzAqD\\qBVu@NkAV_B`@sAb@aA^aA^aAb@oAp@}@h@}@j@{@j@_@Za@Xi@b@]Vk@h@gAbAs@r@uA|A_@b@m@v@i@p@c@l@g@t@k@z@s@hAy@lAo@`Ao@`Ao@`A_@h@gAzAgAvAkAtAo@t@g@j@oApAu@v@{@v@oAdAmAdA}@p@aAr@w@h@m@`@k@\\iAn@{Ax@cDzAgChAuCrAoD~AkBz@yBbAiAf@{Ar@gBv@qCvA}@f@i@\\aC~AiAv@oAbAsBjBcAbA}AdBaAlAsBlCy@hAcBnCy@vAeAhBkAbCi@jAu@`Bw@nBkA~Cg@vAg@zAa@rAQh@[fAc@bBW|@Op@Sx@_@~Am@tCSbAWpAWnA{Gl]oAnGcAtEkAtEeApDu@bCa@lAg@zA{@xB}@|B{@nBiAbCwBbE_BpCoAnBmBpCeBxBy@bA{@~@u@x@eAbAsAnAuBfBcAt@oChBiBhAeAh@{Ar@_Br@u@XiA^aBf@cAVo@LkATwAVwARsBTmAHeBFaBBqBAsBKwDQkAEYAaACwB?O?O?e@BeBFqAJwALuBXYDsB^eB\\uCj@]Fw@Nk@LgB\\MB{Cl@yCj@cBVg@D]Bq@Dg@By@?c@?cACy@EaAK{@Mu@OmAYuAc@y@[aAe@_Ag@m@_@[SaAs@{@q@k@i@[[iAqAs@{@Ya@q@aAm@{@qAmBeA}AkAoB{@uAoAoBmAmBw@gA]e@oAgBmA{A_AcAeAcAu@o@w@o@g@_@aAm@y@g@m@[yAq@cBm@iA[qAYeAS}@K_AGoAGs@AsA@eABO@w@FoANgAN{A\\eAX_A\\g@RYLuAp@u@`@eAp@}AhA}@v@{@t@g@j@w@z@}AlBW^]d@mB~CqAbCg@bAiAvBwAnCYj@kAvBy@|Aw@tAYd@i@x@cAzAg@p@eArAq@x@iAnAcAdAcA~@qAfA_BpAcAp@iAr@y@b@g@V]RqAl@kAb@gA`@mA^aATyBh@yCp@kAVuAZmAXgE~@{FnAsFpAsFlA}Cr@[FwEfAqE`A_MpCmAVyBf@mBb@oCn@yBd@iDr@sN`DaB\\oB`@aBT_CXaCP_DJyC?aBCyAGiAGqBQmAOgFs@}@KcCScAEG?oCEK?cDBoBJqBNsAP}B^yAXcAVoBj@gA`@k@RuB|@QHoClAqB`AoCxAcB~@eCxAiBfA{DfCwDhC}BbBqFfESN}ArAsApAkAnA_AhAIJkA|AaAtAeAbB}@zA_@r@_BfDaAxB{B`F}ApDo@tAo@pAm@pAeCtEcAfBg@x@mApB}@tAu@dAcAxAu@lAa@h@sAjBeE|EcClCoBlBmAhA}BnBsAdAgAx@sCnBmBnAmBfA{C~A}Ax@sBz@cBn@cA^aBh@yCz@oB`@sBf@cDj@u@Po@NoBj@{Bx@iBx@{At@yAz@o@d@qA|@oA`AaAz@y@x@w@v@q@t@o@t@CDcAlAgAvAw@jAq@fAy@xAu@tAaAfB{FtJuBxCkGnI{AdBgAlA}AxAyAxAgB`BeBzAuAfAkAz@mA|@iAt@_Al@uAz@mCzAiCpAq@\\o@\\oAl@wBhAoAl@cCpAiB~@kB`A}Av@wAt@ID}BhAgB|@gB|@_Bt@y@\\}@^iAf@{@\\oG|ByBr@gCp@kCr@wBf@}A\\w@Ho@LkDh@eDd@QBk@H_AL_AL_ALcANmAPqAPy@JaEh@mIjAa@F[D[DaEj@cEh@_ALoBXoDf@}Df@wARgBVuAPoBXiANcH~@k@HmEn@cBTaIfAoL~A}ATmAP_BRoBXkIhAm@HaALeAPM@{@L[Fs@Lc@Ju@Rc@Le@Na@P_@P]Nq@`@[PYPQLMHABw@l@wAnAaA|@m@j@s@r@{@v@_Az@s@j@iAv@c@ViAh@eAd@A?y@\\k@Lu@Rg@J}@Lo@J{ARyANyAReAPg@H]Hw@TSF_@Le@R[Le@TmAp@s@d@g@^g@`@i@f@c@`@a@f@e@f@GHUXc@l@Yb@_@h@c@t@g@|@k@hAYn@]z@a@~@m@dB_@nA[nA[jA[xASdAUnAYzAOlAUhB_@lCSdBYdCObAQvAMdA[zBYfBe@jCk@|C_@jBc@pBYlA_@vAOn@[jAYdA]nA_@jAUt@Yz@[`AWt@aAnCmAhDg@vAoAtDq@vBm@pB]rAg@jBa@dBa@fBYrAYtA[`BUpA]rBW~AYlBYzBYvBk@rEYdBm@tEgBvNWrBWpB}Df[{@vGm@xEm@rFq@dG]fDc@jEk@rG_@tE[bEMfBWjD]~E]bG[vFCf@ObDQxDa@hLOpEO|GG`CGnDE`CEhDEdDCbDC~EApDAvGAhBAnCApBExBCpBG~BKfDKjCOnCShDOfBShCWzCYrCWbCY~B]fCUdBWbBYdBc@dCe@bCWrA]`Ba@fBg@rB]rA[lA[fAg@fBs@`Cy@dCs@rBaAhCq@bBkArCm@rAo@nAeAvBq@lA{@`B}@zA_AzAi@v@u@hAaApAaArAw@`Au@|@w@z@{@~@k@j@iAfAoAjAu@l@iA|@u@l@eAr@kBlAs@b@q@^C@s@`@YNaD~AuEvAaB\\s@JaBLs@@k@@y@AgAKu@?[CC?g@Gw@Ou@SkA_@y@]cAg@o@]o@a@y@m@m@g@s@o@q@s@}@_AqAsA_AeAeAkAaAcA{A_BmAsAsAuAaAkAiBoBkAgAo@k@kA{@m@a@cAm@YMo@Ya@Oo@Us@Sm@OaAOs@Ig@Eq@Eo@Ai@?i@Ae@@a@Bu@F}@Nu@NUFc@LcA\\_@NoAj@o@\\k@^aAp@a@\\a@^gAdAYXGFQPm@n@cElEmBrBeAhA_DpC_Av@_Ap@{@j@eDlBa@Ro@Xs@XoAd@yAd@}@Ru@RaARmBZu@Jg@DeAJ}AJgDPuCNcI\\sCNkCJuDPgDPyBJsDT}@B}@FsBJaSt@qJd@oJb@kKf@{GZ]BcF^eCLeDL_CLeGX_H\\s@DaEPuGZuBP{@JgANwB^e@J}A\\eAXyBp@k@Ro@T{@\\{Ap@m@V{BjAwBjAgHrDABCDEBIDQJQJw@b@mAl@wDjBqB~@a@T{@`@cAd@wAn@sAn@aCdAiBt@wB|@wBz@iAd@iAb@mBt@mAb@iC~@kDpAeDhA}@XmBl@]JKBe@Ng@PcAZoBj@mBj@m@Nm@Lm@Nq@L}@RkATe@HqAP_ALaBRmBN_AHaBH_BHcAD}AD_A@_B?aB?gBE{@A}@E{@Eu@Ew@GkAIo@Gw@Km@GeAM}@M_AMmB]_AS}@S{@QyA_@_@I}@UoBg@uI{B_Ba@kBe@{Bm@o@QoA[SGyCw@iAYiAYkEiA}FyAs@Sk@MGCUGaAYcAUaAWgAY{@U]KeCo@mCq@gCq@}Cw@_@KkFsAeAY}Aa@_Ba@s@OeCi@aAQ[EGCWEy@Km@Iy@IcCYkBOgBM_BIm@Cm@Ac@Ao@?eA?[?[AU@gA?S@k@@m@@I@_@@kEJiN\\qBFqAByADms@hBI@]@a@@o@@w@BIAKEe@BgAHeCPeBRaALw@LgANy@N{AZiB`@UFoBh@wBn@gC~@eA`@aBp@{@`@q@Z}@b@uAr@}@f@eBdA_Aj@k@^_An@{@j@aBnAkBxAw@p@iB~A_BzAy@v@{@~@IHy@z@aAhAw@z@}AbBqBxB}BhCiBrBqBrB{B|BmBhBeBxA}@t@u@l@oA`AeAv@aBjAsAz@IDeAp@oAr@wAt@eB`A{Ax@yAx@yAv@yAx@kH|Dkd@xV_CvAi@\\y@f@u@d@eBfAuE|CeCdBqCpByB`BcE~C}D~CmBbByChCmFxEyDrDiDfDqDtDcCjCgAhA}DpE}EvFwCpDwAhBaAnAyAjBcEtFuBvCwApBcAxAiDbFmDjFgErG_DvEi@x@U\\_AlA_AlAeBpBsAvAYZa@^c@b@]XaAz@{@r@gAx@{@l@y@h@{@h@k@\\a@TCBe@Tq@\\g@T_@PiBt@m@To@TmA^e@Ly@RiB`@yB^eBRo@F_CNoBFaBBkCFaCDcCDcDHoABqABqCF{ABqDH_DHoCHcAFyAHoAHqAHyALgAJoCXmBT_AL_@D_AN}Cd@}Bb@oB^mAVoAXa@F{A^{Bl@oA\\{@VoA^m@RkBl@kC|@{Bx@iBt@kBt@}@`@}Ar@mAh@uAn@cAf@kAl@_CnAaFjCyBlAcCpAiJ`FeQfJeCnAw@\\oAj@q@Xs@Xq@V[JaBj@sA`@mA^aAX{A`@{@Ty@PeB`@k@LoB^a@Fi@HuBXoBR}@HkCTi@D_ETaCJwBHqCJgCJgAB}CJwCHwGNaINsEF}FFgFBuE@yE@oHAgGCgFEoDEgCEwAEkAEgBIqAGoBO}@IcAIaCW}BYcC]qB]}H}AsMmD}JoCuHuBaHoBsF{AgFwAgD_AyBm@qA_@q@QiEmAgBa@eCe@{B[yBU{BO{BIw@AyA?o@@}BFsBJoCVuC`@kCh@mBd@uCx@cElAwC~@yFpByEhBiEdBgCjAgClA{At@e@RaEvByAv@}BpAmAt@sEpC_DvB}A`AOJsAbAoDlCsB`BoDrC_EhDoDbDaBdBABwAbBW`@cBjCq@vAYh@k@nAg@nAUl@o@jBc@xAs@lCS|@]bBGX[tBQhAi@fEg@fEcB~N_@vC]zBo@bDg@tBU|@]tA_AtCm@dBi@rAe@dAmAbCs@lAkArBcBjC}@zAuDhGmEpHkB~CgApBKT{@dB[t@{@rB_@bAq@lBKXc@vA]nASt@]pAw@rDS`Ae@hCOv@_DrRi@bDgAtGy@|EEXgAvGgEfWwAnIkEtWgBtKoBfLuAnHy@fE_AxEOt@c@|BiArFkBlIWpAq@rCw@hDUdA_@xAMh@wDjO}A|FqAnEsBvGwCpI}B`GoDrIYl@oCvFoBzD{CnFq@dAo@fAeAbBuAtBmDrFgHzJ{CdEuAdBk@v@cC`DsDvE}EdGm@t@sDrEo@v@wBjCc@h@QRcAjAg@l@_BhBsKrLkDtDwAxAa@d@]\\aAbA{D~DON[ZWVcF~EiCdCy@x@WZ}@x@OL{@t@aA`AiBvAaAr@aAn@}BvAeE|BaA`@s@VmA`@cA\\m@Ti@R_B^s@Pc@HaBZoB\\sARK@cCTsAF{@Bo@E}@@_@?w@?_@?g@A_ACo@C{@EeAIYC}AS_AM{@McB[gAWqAY}A_@oBe@g@K}@S_Ba@sBg@cB_@wCq@wD{@o@OyA[{@UgCk@a@KWG_@K_@Iw@Q{A]c@KwA[y@S]K[IaAU]IyA]u@QaB[c@E}B]a@Ea@G]Ca@C}@K_AEm@Eq@EaAEgAGo@Cq@CWA]CwAE}@C[A_@?]?y@?e@@i@@e@By@BeBLm@D{@J}@NiAPaAPc@J]HmAXk@LgBb@wAZuBb@UDKB]Fq@L{@P{@RqA^e@NiA\\mA`@_A\\y@Zw@\\]N[NC@w@\\c@Tw@`@{@d@{@h@uBtA{@j@wA`A_@VgAt@[TkAx@w@l@qAbAi@b@u@p@YX_@Z[Xq@r@]^o@r@a@b@SVgAtAUZ]d@e@r@W^W`@_@l@Yf@m@bAo@hAq@lAgBdDWb@e@x@c@z@_AfBkAxBeBbDiAtBwArCeBtDqA|C}@xB_AhCm@hBg@lBg@~Am@`CSt@{@`DiDdOiCjJ}@zCMb@Wv@Wt@Y|@uA`EiAxCw@tBi@rAWh@_ClFsBjEcBbD{@~AIN}ArCc@v@{@xAoAnBkDhF_ArAsAlBsAhBQXcCjDy@lAiBnC[f@{@nAWb@aA|AkDpFIN_BlC{CjFyClF}ArC}ArC}ArC{@~Aa@x@k@dAaAjB}@~A_@t@u@xAeArB]r@mAdCyBrEsBfEYl@kAfCaAxBYl@Q`@MVO^o@tAuA~CkBjEKT}ArDqA`Dw@hBoA~C}AzDo@`B{BdGYr@ENc@jAmAjD]`AsAvDqA|Di@zA[`Am@hBk@fB_ArCy@hCM^_BjFmArDs@~B{BzFqAtCeArB_AdBwA|By@rAiA|AqBbC}AdBoGpFaBhA{C`CiCdCeBrBcBbCy@vAq@jA_AhB}@rBcAfCmClIi@|Aw@rBe@hAs@~Aw@~Am@hAs@hA}@vAeAtAaAlAeAfAmAjAcBvAkDbCaAp@e@\\g@\\_@XaAx@o@j@y@v@k@h@wA|Ag@l@g@j@{@hAi@t@i@t@SZYb@aA|AgAnBaAlBg@bAg@fAe@fAiAvCSj@Yv@m@dBGRGRk@hB_@vAk@vBk@dC_BnHwBpJS|@S~@i@`CaBbH[rAwCnLkDtMc@`BADmAnEaAjDu@jC[bASr@m@jBwAxDw@hBqAhCk@bAOXq@dAa@l@oAdBw@`AWZy@x@_A|@cAz@IHw@j@m@`@GF]RWNaCvAuBnAy@h@WPyAdAgAx@iAz@sAjAgAbAyDrD[\\{@~@g@j@oAxAmAzAs@~@s@~@e@p@kAbBo@`Aq@bAo@dAo@fAa@p@qA`Cc@x@u@xAw@~A}@lBCFu@~A{AdD}@hBy@bB_AbB}@~AKPkArBmAnBoAlBkBlCqAbB{CpDsBzBsBrBwBlBmBzA{AhAUPYP}AbAo@^_@T{Az@}@b@cAb@eAd@UJe@R_@NWJa@NmA`@s@ReAXiAV}@PwAXwAPqALwCNcADU@gBNk@DmANcBTqAVyA\\}A`@o@TgC|@qAl@cBx@oAt@mAr@_@TiAx@cBtAmAdAONs@j@]Z_@\\kAlA_BhBeArAe@n@cArAaAtAk@|@Yd@MRQXk@`Am@fAo@lAw@|Aq@vAs@~AaA`CkA~Cu@tBqA~Dg@bBITW~@a@`Bq@jCe@vBc@nBc@tBeAvFa@|BW~AYdBG`@]~Bo@xE]rCIl@MjAGh@[zCQlBYpCY`DQ~AOxAM~@UdBU~AMv@Kn@]dBOx@]~Ai@|BMd@IZg@bBSl@m@nBaAnCq@`BUj@CDA@mAnCkAzBo@dAW`@U\\sBvC]`@gAnAc@f@mBjBsAfAqBvAoAt@yBfA{Aj@kDjA{Bp@aDx@WHsA\\s@RyDx@gF~@wAViARoC`@_BRo@Hs@H}@HwAHyAJ{ADsDFwA?Y?]C]?g@AoDOeAGeBO{@IGAmEk@aAQGAQEMCUESEsCe@}AWgAQw@K]EaAI}@Io@Eo@EgDMiCCaB?_A?o@BaAB_AD_AD_AFm@DaAJ_AH}@Js@JmBX{AXaB\\{A^mA\\oA\\mA^yAh@oAf@mAd@iAf@{@`@]N]Pu@^m@\\uAv@wAx@gAl@gB|@}Ap@s@Xo@Tm@Ro@Ru@R{@Rw@RgBZqBX{ALaBJoBDcA?aBCaAC{AIoBQkBYcBW}Aa@aCo@oBe@oA]eBc@q@QuEkAaBa@{Cw@cCq@_B[YG_AQkB[qASsASkCWs@GC?y@Go@Io@Is@Kk@Iq@IsAYcB_@oBc@mBe@}@WmA_@q@Sk@So@Wk@Um@Uw@[u@[w@_@}@c@}@c@m@[qAq@MIkB{@]QsDgByAi@_DaAqA_@wA[cCa@cAOQCiH}@}BSu@GiCKaEGw@@gABaCJ{@HiAJ_AHw@H_CVsC`@uBXgALi@Bq@D_A@_ACs@CiAG}@MyEw@uAUoDq@]IqDk@aBa@{Bg@oB_@qE}@yBe@AAcDu@wNsDqDiA}DiAqBo@oDmAyBy@eC_AoCeAsCcAAAMEoBq@{Ai@u@WwB{@mBs@cC{@cBe@cAYsA_@qCc@aBW_C]qD_@cCSg@CqAImAAs@?s@?gAAcBByAB{BL}@DaBLiAJiANc@DE@sARkB\\iDv@mA\\cErAqDxAqD|A}B~@m@VGBmBr@gAh@{@^iBp@yDpASFUH{Bn@eD|@gCl@}Bh@oDr@s@LqAVgDj@a@FiDf@aGr@uCTiCN_GP_ADiEF_E?eFIcBEmCIg@C{CQgCQiEe@y@IuKyAeBUoBQeCSi@As@EqCKcCE}@?{A?mB@_ABsCDm@D}AHq@@oCBiFH_B@}@AaAC{CMeAGkAKs@ImAMiBUiAUkAS}@S_AUmAYoA_@gAYmC{@mAa@iCaAkAg@aBq@uAq@}@e@wAw@YO{CcBcD_B}BgAuAo@eAa@qBw@{Bu@iA[{FwAmE}@}B[g@GwDe@qEa@cBUoB_@wAc@eCw@iCeA_CoAe@WkAq@sCwBuCcCyBcBEEeBoAWQmBkAwBgAuAq@_@OqBw@g@QIE{@[gBg@}@U}@SaCc@yASqAKaBMKAgAE{IG_GEgG?e@Ag@AoC?iGEe@Ao@?oIGkACg@?}DCmAEmAIu@Gu@I_AOeAO}@Sy@Sw@Ss@Ug@QkAc@oAk@kAm@c@U}@i@s@c@y@k@e@]_Au@g@a@a@_@u@s@i@g@i@k@[_@u@w@o@w@eAuA_AsAiBuC_AaBe@{@m@iAg@eAKSk@mAe@eAu@iBWm@Ws@e@qAmBoGaAaDi@iBa@oAe@wAaAkCg@sA]}@{@oB{@oBaAsBqB}Ds@qA]m@Yc@U]o@eAe@u@q@cAo@aAi@q@{@kAa@g@_CmCsAuAuAqAyAqA}BoBy@m@sBqAyA{@s@e@}Aw@mAk@}@_@iCaAqGqBg@Qe@SeBy@k@[eAq@k@a@gBwAuC_CqB{AcAm@wAw@_Bo@y@WeAYyAWkAOmAEk@Aq@AuABm@Dw@HiAPs@Ni@LcAZg@PcAb@eAh@g@X_Al@mAx@{A~@s@^eAd@a@PyAd@c@JwA\\_Dl@_CHuCEcBMo@Gi@I{@QaBc@KCcDuAUKSKECWMc@SkBmA_CqBg@g@}A_B_BgBoD_EqB_CkAoAsA}AuEiF}AgBk@o@oC{CwBcCoBwBkG{GeBcBm@k@oAgAwAiAcAs@oAy@eAo@q@_@_@Q{@c@{@]yCmA}@[iA[e@OyBc@eAOaAMeAI}BMcBCoA?mB@qAFmAF_AJy@Hq@Fo@FaANaANQBG@YFkB^o@J{ATa@H]F}@To@RgBl@YL_@Nm@VKFoAl@cB~@MH]Ty@f@wAbAm@d@[Xw@p@i@f@}@`AEDmAxAg@n@}@nAq@~@oA`Bo@|@s@dAaAxAo@bAoBxCm@x@o@|@s@|@Y\\gAlAeBdB{@z@_A|@aBzAeBvAw@n@k@b@cBnAgBjAiBhAgC~AyBlA{@f@kAt@y@j@q@f@c@^mAfA}@z@mApAw@`Ae@l@u@dA_AvAy@rAq@jAq@nA_@t@oC~FmBhEgAhCq@xASf@u@lBqAlDq@fBy@bCe@vAy@fC}@|Cs@nCa@~Au@`DK`@I`@eAfFq@bEc@xCq@bFs@hFw@fFs@fEMt@Ot@iA|FcArEy@dDsAbFiAxDo@rBiAhD}@dCcAnCq@dBoAnDoBlGuBlHQt@qAbF}@`De@zAu@|BqAnDwA`D_ApBgApBaA~Ak@~@_ArAaBvB_BdBu@v@eDfD_@b@"
                     },
                     "start_location" : {
                        "lat" : 52.668364,
                        "lng" : -2.072026
                     },
                     "travel_mode" : "DRIVING"
                  },
                  {
                     "distance" : {
                        "text" : "103 km",
                        "value" : 103347
                     },
                     "duration" : {
                        "text" : "57 mins",
                        "value" : 3421
                     },
                     "end_location" : {
                        "lat" : 54.6502013,
                        "lng" : -2.754541300000001
                     },
                     "html_instructions" : "Keep \u003cb\u003eright\u003c/b\u003e to stay on \u003cb\u003eM6\u003c/b\u003e",
                     "maneuver" : "keep-right",
                     "polyline" : {
                        "points" : "wtkgIdmmOWHEDi@h@g@h@UToCvCoBxB{@|@{@|@_Az@u@r@g@j@sAtAcCnC_BvBuAvB]j@oChEk@`AWb@y@xAsAnC{@jB}@rB{AzDeC|Fw@`BeArBy@|AS^OVOVoAtBkBpCkCvDuBlCiAtA}@`Ae@f@_B|AyApAgBrAwAbAcBfAqBfAsAp@uAp@uAl@oAh@iBn@{Af@uA^uA\\aB`@qA\\_Bb@mAZ_B^mAZ_ARo@PmAZmBh@eD|@qD`AyBn@oBj@iEbAsEfAwEzAsDnAyChAgCdAaA`@oBx@iAd@uD`B}BdAeDzA}C~A{BhAyDrBaB~@gBdA}A~@k@^oBlAiAr@aAp@{@h@mChB{AfAKF_EpCmCvBcOtLqAbAaBrA_@ZgCrBgBxAkEnDoCxBsAfAoB`BsBbB_BnAaAx@gBvAw@p@kA|@_Av@kA~@u@l@w@l@WP_Ar@k@\\i@^eAr@y@f@mC~A_CpAYNmAl@y@\\e@TkAf@gA`@qBv@wBr@k@PgCv@aCh@{@Ry@P_BZaC^YDoAP{@J{ANq@Fe@BcAF{@DgADs@Bo@@}AByA@_A@u@?wA?_ACaFMeHQwFKoDGY?w@Cy@AeBImBGoBKqBIkDMoBEoBEaCCoCGmACs@?k@?a@@c@B]@m@D_@Bo@H_@Fe@Hg@Jk@N_@J]J_@L_@N[J_@P]N_@RYN_@RQJYP[ROJSLSNOJ[T[Xk@b@WR_@ZWRYTa@X[Xk@b@c@Za@Zk@\\k@`@]Ri@\\o@^i@Vm@Zq@Zy@^y@\\o@Va@Li@PoBf@yAZaB^u@Pi@LaB^uBf@oBd@}Bl@}@TkAVsA\\_ATo@NuB`@{AZ_ARkBb@mAZaAT{A\\qAZiDx@iB`@aB`@mBb@mCn@qBd@mAV_B\\oATeB^s@NcBd@mA^}Ab@oAZkBf@oAZ}AZ}B`@qB`@aBZiDt@mAZoAZiAVq@No@Lk@L_@H]Hm@Nm@Po@Pm@Pk@Pq@R{@VaATaAV]H_AT_AR_AT_APq@L}@Pq@Jo@Lo@Ja@Fo@H]BsBT}@Ho@Fm@D_@@_@@m@?o@@_A?o@?]C_@Ao@Am@Eo@Ga@Cm@Ga@G]E_@G_@Io@M}@Q_@Kg@Mi@Kg@MgAWm@K_AS_AQmAU}AWa@G{ASy@Gi@Gg@AaAEiACs@Cm@Cs@Co@Cm@Am@Ec@Co@C}AGkG]mBO_AGs@Im@Go@Iq@Ka@Gc@Ie@Iu@Mc@Ik@MWG_@I]I]Ka@K]K_@Ki@Oa@Mk@Sa@Mk@S]Ma@O_@OYKSI]OSI]M[Oo@W_@O]Q]Om@Yc@We@Sm@]iDiB[Q]U]Ui@]i@[o@_@o@a@eBy@m@Yk@U]M]KQGm@Oq@O]Io@Ka@Cg@Ig@Ea@C_@?_@C_@AoAA_@?_@@_@@_@B[Ba@BQB]Dq@Lm@Jm@Lo@N_@Jm@Rm@R_@LUHWJWLUJWNUPyBvAw@j@i@^]Zg@d@]Xi@h@k@n@UVMNY\\UX]b@Yd@CBm@~@q@bAc@t@_@p@qE`IeAfB{@xAo@dAg@r@e@n@e@r@q@`As@`Ag@n@e@p@g@l@g@p@Y\\e@n@g@j@q@t@}BhCw@x@e@h@QRe@h@i@h@u@r@w@t@k@f@i@f@k@f@[V[V[Xi@`@y@p@k@b@m@b@{@p@eA|@aFtEcAbAi@j@cAdAy@|@w@z@s@x@o@t@w@`Ai@p@q@|@g@n@s@|@i@r@e@j@w@bAc@j@o@z@g@n@aAnA_AjAaAnAs@|@s@~@e@l@g@p@aAjAmA~A{AjB}AlBk@p@q@r@w@r@cA~@w@p@{@p@aBjAkAx@kAr@eAl@aBt@kAf@mBr@k@Ro@Pk@N_ARiAVc@JyAJoAL}@Fa@B_@Bo@@mAD_A@m@@q@Cm@Aa@A}@Eo@CaAG_ACo@A_@Co@GqAIg@Ca@Aa@CaACqBIoAGqAG}AIaBG_AEaBKoBI}AImBIuAE_AA_BG_AEq@@oACu@@o@CcLGeECwB@a@@qACoBBkBBcCFgENu@Bu@D}@BqBDiAB{@DeDJ{AH_BH}@FqAJ_BLmBPaAHo@F_BPmALiBTaBNaBPi@HkBRyBRuAPiBPyAReBRaAHo@Hi@FcAHaBRoALaBRqAN_BN_AHo@Fq@@o@Ba@?_@?q@Ao@Ao@Aq@CaAGo@Ga@E]C_@Gq@KaAQ_ASo@Os@U{@W_@Im@Sa@M_@K_@M]Mm@So@W_@Oo@Um@W_@Qm@Y_@Sm@Ym@[_@O]QuC_Bo@c@k@_@}@i@m@_@y@g@m@_@m@_@o@c@w@k@m@e@gA}@y@q@k@g@y@q@k@g@]Wy@q@i@e@k@e@k@g@k@e@i@g@k@e@m@e@i@c@w@s@g@c@w@o@[Yk@e@i@e@y@q@i@c@w@q@[Y]Y[Wk@e@i@e@k@e@k@e@g@c@_@]sBaBmS_QgA}@y@q@eA{@}@o@y@k@k@_@k@]m@]_@QoAo@m@[]Oa@O]Mm@U_@Ma@M]K_@Kw@Si@Mo@M]Gs@Kg@Ie@Go@Ie@Ei@Ea@C]Aa@C_@C_@Ao@Ci@?m@AWAU@U?S@g@Dm@HaBHuAPM@iARwAZkBd@_AXk@ReA`@eAb@{@`@{@b@uAv@}A`AkAx@gAz@_Av@SPk@h@u@r@eDhDg@h@]ZcA|@k@`@k@b@m@^q@^YLg@Ta@P[Jq@R]Ja@Hk@La@F]F_@BQBM@a@B]@_@?c@?OAm@Ao@C_@Cg@Gw@KmEq@oC[_BMo@Ek@Ec@AoAEg@AwACQ?o@?cAByAFsAHiBPoAJi@DwAJ_F`@w@Du@FsE\\qE\\e@BYBO?_@Bq@?S@[?a@Ao@C_@Ce@Gu@Iq@Mq@Qk@Qa@M{@[k@Wo@]_@Si@_@]Uy@o@i@e@i@e@}A_BeBiBsAwA{AwAcA{@cAs@{@e@}@c@_Aa@UIWIoA[m@M_AO_AGWC[AmAAo@@q@Do@Dm@HqARo@L}AZoB^m@J_AJo@F_@@a@B_@?o@?o@AqAG}@G_AG_BMqAK_DWoAI}BQeCOqE]_CS_BM}BQqFc@{Im@aHi@mE[_F_@}BOaAMmC]aBQ{@ISEc@I{@So@Q]Om@WqAm@g@YYSg@]aAq@cCkBgBsAiAy@kAw@iAo@iAk@qFaCcC{@gBe@uCq@uCo@oBe@yCq@_AWkCs@_AY{@YSG{@WOGOGg@Ui@YoBeAmAq@mC{AgAy@uBcBiAaAaB}Ag@i@gAkAkAmAs@w@W[i@o@y@eAg@s@U[qByC{A}B}A}BCG}@mAg@q@k@u@cAoAq@}@m@s@UYm@s@i@m@q@u@i@k@g@i@OOYYi@i@[[o@m@_A}@s@m@{@u@QOOO{@s@oB_B_Aq@OK_@Yo@e@u@g@q@c@KG]U]UyA}@qBiAaB{@OIi@Yy@_@{@]o@Ys@]q@Wi@Uk@Sq@Wk@Sm@Sg@Q}@]g@O[My@Wk@QWI{Bo@w@SmA]iBi@oBg@cB]kAYq@OoB_@mB_@oASaBYoAS_BS_BSoBWo@IaAK_AI_AKaBMaBOgEWa@CsEOqDIqBCaBC_A?oBA_B?aB@_B@aB@_B@qB@oB@qCB_C@_B?sA@kA?c@@mD@aEDoDB_C@_E@oBCa@C_@A{BMi@Eq@Ie@GaBYo@M]K_@KoA[kA]mAc@kAe@yAo@oAi@kAe@WKWIMEo@Qq@Q}@Qo@MoAQoAMoAM_BQy@Mi@ImAYuA_@w@Yk@Wk@[y@g@w@i@e@_@k@e@i@g@i@i@i@k@u@}@u@_AmAcB{@oAaAuAcAuAs@}@}@gAeAkAw@u@}@y@{@s@g@_@a@]CAkAy@{@i@iBeAeAk@a@Uo@_@uAu@mB}@yAo@}Am@}Ao@}Am@mAg@iAc@kAe@g@Og@MkBg@k@MkAWmAY_B]{AYu@Qw@QyA]g@Ko@KgAMm@I_@EoCW}AMq@E_@CoAIm@CaAGo@C_AAa@AiBCsC?gA@cABu@@aAB}@DaBHg@B}AFy@D}AFe@Bk@@eABk@@a@@e@@e@?qA@oAC}A?qAAm@AaCEeBEq@AwCIo@Co@EiAEiAEqAImBK_AIaBK{@IcAKmAKqBSmBUoAQoAQ_AMo@K_AM}@Q_BWm@Mo@M_AQ}@Qo@O}@Q_ASo@MoAU}@QaAO}@O_AO}@OoAQsAQqBWUCWAMA}AIqAK{DQ}AEsBGoBEoB?_C@qB@aB@qBFcCJ_EH}BDuAAiACoAKgAMu@MqAWu@QsBo@_A]eAe@{@c@eBaA}AmAuBcBoBmBqAuAm@o@_AcAoA_BiB}BmBoCyA}BiAkBcAiBmAgCCGi@qAcAeCo@gBCKWw@Oi@Qi@Qk@o@}Bc@gBg@yBI_@Mk@Mo@Om@UeAOu@Qw@S}@Qo@Oo@Qm@Ok@YcA[_ASm@Wu@Yu@Si@MYYs@Ue@Qa@Uc@We@Wg@_@k@[i@o@_As@aAuAoBg@o@MOg@q@aAoA_AiAw@_As@y@[][]i@i@[[i@g@u@o@]WMIOKOKMIOI]Sm@Yk@Y_@O{@[{Ac@QGa@Kw@Qs@Sa@K[ISGMEa@M]KQIOGYMSKOIMGMIOI]UOKYSOMMKOKIIQMIIOMOOMMMMMKMOMMMOKMMQKOMMKQMQW]KSKOMQIOMSKQKQIOMSUe@KQKSa@w@Se@Wk@Wg@Ug@a@y@Wg@Se@c@y@Ug@Ue@o@gAo@gAYe@c@s@k@w@y@gAYa@o@u@a@e@MMY[[[g@e@MMOM[YOM[U[U]UQOSMe@YmAo@o@[WMe@Sk@Uo@Wo@U_@MeBi@a@KQE[IQEi@KSCQE[CSEMAa@E]Cs@Ek@Eo@Ci@EUC]C_@EQAOCMAOCOC]EOEQE[GYIUGQEYKKCUIOGOG[MMGQKQG?AOIMGOKMIMGOKOKSMGGOKMKMKOKMKMMCCIIMKMOMKMOMKKOKMIIQSMQKOMQIO[a@c@s@We@Ye@k@aAWg@[m@eBgD[m@]m@a@s@qAyBs@kAo@gAc@q@OScA_Bg@s@u@cAaAmAu@}@UYw@_AuA}A{A_BuAwAy@y@aB}A_A{@q@g@gA}@w@o@{@m@y@m@k@a@k@_@}@q@w@i@gAw@o@e@cAs@iAy@y@m@iAy@y@i@aAs@mA{@kAy@y@m@y@m@iAy@gAw@iAy@{@m@eAw@cAu@}@u@i@a@_Aw@g@a@u@q@u@s@OQYY[[_@a@o@q@Y[[_@c@g@Y]gB{BQUq@{@u@_Ai@s@q@_As@aAc@k@s@cAu@eA}@oAuAmBmDyEo@_AYa@Y_@aAqAwAgBuA_Bi@i@k@i@eA}@}@q@gAs@sAu@g@Uk@Wc@Qa@OaDoAmAg@{@a@g@Wc@Y_@S[Si@[m@c@k@e@cAy@w@s@o@o@}@_As@y@gAsA_AmAq@}@w@_Au@{@w@y@s@s@KIg@e@k@c@i@a@k@a@i@]i@YkB_AgAe@{Bw@kC}@i@SaA_@eAe@cBy@eDkBuBsAuBuAeD{BqCqBeBsAYUeBuAqC_CsF}EOOWSUUKIKI[WSOYU_Am@gAo@uAs@yAo@{@[iCaAmAg@c@Sq@_@gAq@w@g@eAu@}@u@eAaAsAuAoAuAm@w@m@w@c@k@c@o@u@mAsBkDwByDy@uAoAgBaAuAiB{BcAkAiAmAeBcBqBcBiB}A{@y@cA_Ac@a@a@e@e@c@}@aAu@}@m@s@sBoC}BcDgBqCmAkBaBgCwAsB{AoBy@}@{@}@e@g@w@s@o@i@iA{@e@]aCyAKGeB{@e@S_@OgC{@wA]yA]iDw@}A]mBe@}D_AeFiAyCs@eDu@kB]iAKy@Cq@Ay@?qAJmANk@JaBb@u@Vw@\\YLWLgAn@yBzAwB~A_DrBsBbAeA^}Bh@i@Hs@FoAH_A?s@AwAKyAQaAQ}Ae@q@WUKq@]_Ak@c@[i@_@kAcAeAgA}@iAk@s@m@aAs@oAoAcCw@mBs@kB[eAUy@i@oBeBqH_AgE]wA]yA_A{D{A{Gu@}Cq@iCw@oCe@{Au@qB}A}D{AcDsDyHu@_Ba@_A{@gCWw@YcA[iAWaAWiAQ{@UmAKk@WyA_AiHu@eGKy@Ky@SyAWiBi@yCUeAc@kBa@uAa@wAOc@[}@q@aBm@wAg@_A{AmCcAwAY]aBiBk@i@q@i@q@g@iAs@aAe@qAi@aA[_@Ky@Q{@Mo@GmAIi@?_CAaB?aCIcCQk@Ig@GoAUm@McAWu@UiA]uBo@wAg@eDaAo@OmASa@Eg@Em@Eu@AoA@kAHaBReB^{Ah@gAd@{A~@oAz@eA`A{A~AcArAgAbBeAlBeB|De@nAa@pAkAlDgBhFWr@m@tAm@rAS`@kA|Bi@~@u@jAk@|@mBfCi@n@cDpDsCdDiAtA_AnAi@x@aAvAkAfB[j@kAvB_AbB}B`Ei@z@_@j@aB~Bi@t@e@j@aClC[^kBbBw@r@iA|@cBhAgAt@gAj@oB~@iAb@qEpAqB`@}BZw@H_CP}CD_DG_BKgAO}A[_@I_@Im@MkA]uAa@aBm@mAg@_Bq@wAw@}Au@yAw@wBgAmAo@{Aq@k@UUIy@WwA_@cBYoBWsAQuAWcB_@{Ae@yAc@{Ae@sA_@_ASg@Km@IWEmAKqAIkBI}ACeA?cAD_CPuAPeALqAT{Ct@oErAaCt@{Bf@_BTo@He@BgBDiA@y@A[CC?]CkBS}Ba@sA]{@[gAe@yBcAqEwBkCuAmAo@mAq@kAm@cAi@y@c@_Ac@u@_@OI{@c@yAs@{BgAWKKEAAe@UoCsAwCuAe@U{@]y@Wy@Si@M_AQu@Kk@Em@Cw@E}@?m@BkAFu@Jy@Jw@Ni@Nk@Pk@Pk@Rw@^g@VQJA?YPGDqA|@a@\\c@`@oAfAeAlAy@bAmAdB]h@s@lAq@pA{@lBe@fAg@rAu@xBq@zBYhAQr@c@jBa@rBYzA}@tEy@bEy@bEe@rBS|@Uz@Qn@Y~@_@nAc@lA]`AYt@Wl@{@fBq@pAg@|@_AvAsAdBcAfA_A~@y@p@eAv@aBbA}Ax@kDxA{Ar@mB|@iAl@aAh@u@f@{@j@qA`AwAdA_Av@_CrBcB`ByAvAg@j@UVCBWZUV[`@eArAaAnAe@p@k@x@g@r@w@jAq@fAs@jAy@xA{@|A{@zA{@zAo@nAo@bA_A~As@fAi@x@u@fAu@fA}@jAu@`Ak@r@i@p@u@z@u@z@w@x@w@x@u@v@y@v@{@v@aAz@y@r@iA~@y@n@iAz@iBlAqAx@aDlBuAr@kAl@kAh@oAf@y@\\a@N}Ah@_Bh@mA\\mBf@_B\\}AVm@Lq@H_ALw@Hg@FoBNeCRcBR_ALsATmAX_ARcBh@aAZu@ZWJOHwAp@kAl@mAr@aBfAaAt@[Tk@d@YVe@`@oBfBw@v@iAbAwAlAiAz@{@l@y@l@oAx@kAt@iAp@mAp@{At@mAh@oAh@_Bj@mAb@e@NeBd@}@TaCh@w@PgBXmBVWDsAJuBNu@BwBHwBDwBFsAJiALy@L{AXcB`@g@L[JaCx@aAb@_CjAi@^g@\\eAr@y@j@oB|AeJlHqDfCwCjBeDdBe@T_C~@wBx@qEzAu@T{Bb@kA\\mAX_Bd@GBk@RaA\\gBt@q@XoAp@mBlAoA|@aAv@]ZwApAuAvAiBrB{AbBkBrBuApAiA~@e@ZyA|@_Bv@c@R{@Z[FuAb@o@Li@Ja@F_BPkBHc@@iQBiH@mELqHb@cFp@]FwDp@oAZiB`@}@RmEnAoBn@}B~@eBt@qB|@yAp@oB`AwCdBqCdBaDvByBjB{@n@{ApA{ArAiBdB_B~AwClCkAdAiB|AyC~Be@Z{DjCmAx@mDtBkBfA}@b@kBv@_E`BwDrAgCr@kAXeCn@aAVsCn@cAP}@RkAXaAZ[Jo@\\u@`@_BbAoBzAm@j@gAfA}AdBuAnBqAtBkAtB[j@iDzFoBpDwC~E}DfH{@~Ac@v@SZ{AdCcCvDcDhEW^i@p@}B`CuBpBeB|A{C~BiQhL_^tUkD|ByCpBqGhEgCfBqBnAo@`@k@^m@`@{@j@qAx@sAz@_Ap@y@n@y@d@o@Zy@`@oAh@sAb@cAZwA`@YHs@N_APs@J_BPe@F}@JoALm@Fm@DiADeBBo@EuACeA?_F@{AFcHd@WB_Ef@gCd@qB\\iB`@eEjA[HkA`@uEfBsBz@mAh@cAh@mCrAcAl@gAr@_DlBeBlAc@ZGDYTw@j@uC~B{AnAm@h@yBpBgBhB{@x@_BhB_CpCwDlEeAnAyC~CcEjEoBlBmC`CmAdAoBdB{AjASNa@ZwAdAaC~AoBrAoAx@o@^qEhCeB|@oBdAyBdAsAl@qDzAoCbAaJpCqBf@_@LcCh@eDt@yBf@kElAsGrBqHzCkHdD{BlAwBjAaB`Au@b@kBlAoHjFqBzAwAhA}@v@eAz@_CnBgA`Ay@x@o@p@{@~@iApA_DtD{@`AcApA{AjBsC`EgFtIeDzFOZOXs@~Am@nAkBlE[v@oBbFqAhDqA~DkB`GeAlDaBrGqC`LyD~MK\\Ql@Ql@cDvKaAtC"
                     },
                     "start_location" : {
                        "lat" : 53.80444499999999,
                        "lng" : -2.6953854
                     },
                     "travel_mode" : "DRIVING"
                  },
                  {
                     "distance" : {
                        "text" : "0.4 km",
                        "value" : 441
                     },
                     "duration" : {
                        "text" : "1 min",
                        "value" : 41
                     },
                     "end_location" : {
                        "lat" : 54.6522865,
                        "lng" : -2.7603246
                     },
                     "html_instructions" : "At junction \u003cb\u003e40\u003c/b\u003e, take the \u003cb\u003eA66\u003c/b\u003e exit to \u003cb\u003ePenrith\u003c/b\u003e/\u003cb\u003eWorkington\u003c/b\u003e/\u003cb\u003eBrough\u003c/b\u003e",
                     "maneuver" : "ramp-left",
                     "polyline" : {
                        "points" : "wzplIz~xOKx@CLERGPOl@Y~@_A~Ca@vA}@|C_A`DIV]hAk@|AEPCLCLGh@Gn@Gf@"
                     },
                     "start_location" : {
                        "lat" : 54.6502013,
                        "lng" : -2.754541300000001
                     },
                     "travel_mode" : "DRIVING"
                  },
                  {
                     "distance" : {
                        "text" : "1.4 km",
                        "value" : 1395
                     },
                     "duration" : {
                        "text" : "1 min",
                        "value" : 83
                     },
                     "end_location" : {
                        "lat" : 54.6483702,
                        "lng" : -2.780675
                     },
                     "html_instructions" : "At \u003cb\u003eSkirsgill Interchange\u003c/b\u003e, take the \u003cb\u003e1st\u003c/b\u003e exit onto \u003cb\u003eA66\u003c/b\u003e",
                     "maneuver" : "roundabout-left",
                     "polyline" : {
                        "points" : "ygqlI~bzO@N?N@RAP?F?HAPCT?h@AXIlBAd@?R@`@R`CL~AVnCTbBZvB\\vBrAjIZtBbAtHz@bHx@tIx@jH~@bIp@vFv@lFr@fEZnBN|@FXDLBH@DDFLT"
                     },
                     "start_location" : {
                        "lat" : 54.6522865,
                        "lng" : -2.7603246
                     },
                     "travel_mode" : "DRIVING"
                  },
                  {
                     "distance" : {
                        "text" : "25.0 km",
                        "value" : 25041
                     },
                     "duration" : {
                        "text" : "18 mins",
                        "value" : 1079
                     },
                     "end_location" : {
                        "lat" : 54.60932889999999,
                        "lng" : -3.1407105
                     },
                     "html_instructions" : "At the roundabout, take the \u003cb\u003e3rd\u003c/b\u003e exit and stay on \u003cb\u003eA66\u003c/b\u003e",
                     "maneuver" : "roundabout-left",
                     "polyline" : {
                        "points" : "ioplIfb~OHBFBFFFDLLFPJ\\BV@RAXAPCNEZELGLGLMj@E\\ARANATAd@JvD@`@@x@@j@@r@@dBAfB?`BAlBClCEtBO~EOnDEr@OxCO`CKxAWbDk@nGg@|GObCGlAEtACpAAdAAxC?f@@dA?rABhAHxBJ~BLnBVnC\\tCZtBJn@P`ALx@H\\v@zDDV\\hBh@tCNdAVnBn@|GTjCTdEl@rMz@xRj@rN@TP|DBf@B`@VfGZpIb@tKTfFV`GR~EVjFPhDVbFn@rOL`Dh@xLf@lKNzCLpCVhDH~@z@`Hz@zG`BvK^pB`AtFn@|Cn@dDV~APxAHt@PfBXjEn@lJNrBDZTpA\\fBTdBRlBDx@f@nHN~BDx@FlAFzADjBDxADbCDz@FjAVvBRpBZlCFn@f@pE^dDh@tEh@vEX|CJhABfAHv@b@rEB`@b@xEb@fFVfEFdBDzAFhE@jC?nBElBElACxAI|BMrDMrFC~AAb@AlBAzA@nBBnBDxBF`BJxBFxAHnALlBJpATfDVxDPnDH`CDfCFxEAtBApAAnACnBEzAGxBQ~D[xEa@xEWdC[`Cc@xCg@vCUbAQz@Kj@I\\]xA]vAMf@Ux@i@xBGXk@|BCJ_A`Eo@xCq@dDk@xCa@vBa@dCUjAa@|BWtAS`BYhCU|BKtAMxBKfBE~AEtBCv@AtAApB@jA?~@DfCHnCN|DRhDNjBNlBHr@PhB@HJhANnANtAZzBx@`Gv@fFh@hDRrAl@pDZbBP`Aj@tDh@|Cn@nDf@pCVtAn@jDn@nDj@|Cd@lCh@rCp@tDPdAV|Ap@`Ep@rELfAZxBTrBT`CHt@VfCP`Bh@pFXbDz@|JNxBN|BPbFJnCRvDJbC@dA@lAAhEIjH_@|IKhC_@tHk@vIm@`JM~BSfE[jGYtFUxE_@jH[xGKrDC`DA|BB~BB`CBbAFzBLhCL`CBb@X`DTxBVtBl@~Df@zCVzAXfBV`B^pCJx@Ff@@LPfB`@fEP`CT|CRxDT~EPhGD`D@l@BnC?zDC`EErIA`F@bH@hCDpEFhEH|EPvFNpELnCFrALfCLzBLhBTlDV|CRbCXfDFn@^jDTrBNlALfAb@~Dh@xE^|CFd@DVf@nCdAzFd@dCdAnFb@lBh@rB~AjGhBbHbBtGrApF`AlDf@zA|@jCxApEt@nBZt@d@bAt@dB`AzBbAzBjAfCdBjDhAnBrA|BjAdBtB~ChBbCjDrE`DfE~FzHbDhEDDrA|Bl@hAP`@b@~@bAdCl@hB\\hAZfAXlAVdAXtATjAb@vCZhCJz@JjAFr@F~@RzD@\\V`FHrAHfAJx@Jp@N|@Nv@Jj@Lf@Pd@Nb@Xl@|@pBl@pAVh@t@jBVr@Xp@L^L\\Tn@V|@n@`C\\pARx@d@zBh@tCf@rCx@tFh@dEr@rGX~BZzBZtBd@jCd@tBXfATz@|@vCz@bCtAzDn@xB`@bB\\nBRxALpAFz@Dt@FdBB|@@`AAjAC~AGvAKnAKnAIjAMv@Mn@[dA}@~Cw@vCi@|BUlA[lBQzAMrAOdCOjDGlCAlC?pABtCFrDP`FJtBLhBHrAX|CBPd@pETfBPfAPdAVnAT~@Nl@Pj@Vr@j@tAv@~Ad@x@X^p@z@`BhBpAvAHHx@`Ap@`Al@`AXh@T`@|@tB`@tAn@dCTfARdALdAPxARxBHbAHpBF`@BT?Z@p@?n@AlBGxAMjDGlAYnCO|@QbAYpAEPQr@c@vBo@xCi@rDe@nC]xDOtBGtACvAMfGCd@I`CAXKf@MbFWpGm@vMa@nIWhF]vEiAzNUhCw@|Jq@lHaAdK]vD@X?d@@R?D@D@LBNJf@"
                     },
                     "start_location" : {
                        "lat" : 54.6483702,
                        "lng" : -2.780675
                     },
                     "travel_mode" : "DRIVING"
                  },
                  {
                     "distance" : {
                        "text" : "20.6 km",
                        "value" : 20570
                     },
                     "duration" : {
                        "text" : "16 mins",
                        "value" : 961
                     },
                     "end_location" : {
                        "lat" : 54.65271730000001,
                        "lng" : -3.3720695
                     },
                     "html_instructions" : "At the roundabout, take the \u003cb\u003e2nd\u003c/b\u003e exit onto \u003cb\u003eKeswick Bypass\u003c/b\u003e/\u003cb\u003eA66\u003c/b\u003e\u003cdiv style=\"font-size:0.9em\"\u003eContinue to follow A66\u003c/div\u003e",
                     "maneuver" : "roundabout-left",
                     "polyline" : {
                        "points" : "i{hlIlldRBDBD@DBD@FBF@F?FBT?T?TCTCRGRGNINCBCBC@CBC@EBC?C@Yt@KZMd@GJIr@Ix@UjCKrA]rEO`DGrAEhBCvAAhAAxA@rBB`CBtADfBHpBLtBP`CHlANrANpAd@nDRhA`@~B\\`Bf@vBz@zCv@fC~@dC|@tBtBdErBxD|AtC\\l@LJDH`@r@h@~@LZFRn@rAXj@r@lAh@dAj@bAdBdDtBzDr@pAj@`AP\\x@|ABFt@rATh@d@`At@jBDJZdAVbA^fBTpANfANtALrAJbCFxB?xA?xAE|AGvAOjBStBm@bGMnAa@pDe@vEm@hGWtCc@xDKdAi@`EOn@]xAOl@YfAe@zAWl@Wj@c@z@o@fAs@fAs@x@i@h@c@`@eAt@KF_@Pg@T{@XcATq@L_ANmANkDh@iARSDe@LkAXuC~@cA`@}Ar@yAv@y@d@oAx@aCbB_ClBuB`BoB~AeAx@wAjA}AlAaBrA{D|CoCzBuDxC_BnAgCnBwBdBsB`By@n@_CpBqAdAs@h@_Al@eBdA_Bz@qB`AgAd@mBp@sC~@}Bv@{Br@yBp@mCt@_Ct@yC~@yBv@gCbA{@`@w@^kAp@wAdAk@d@y@p@gAfAeAhAwBlCuAnBuAlBgBbCeBjCqBvCiBtCKNiCvDaDpEAB{@dA{@~@SPk@h@sBpAyAx@uBhAs@d@wAjAe@d@{@`AeB|BM`@AFEDILSTWZa@`@gBpAeBp@wBf@kANqBVuC\\q@Jc@FqAR{@Ro@^a@^a@`@w@fAq@p@c@b@{@z@}@x@o@j@g@^cAf@e@Pi@Nc@NYLo@Zg@\\c@`@kAhA{BpCg@t@e@d@a@`@s@`Au@r@i@d@k@d@y@\\YPQJy@t@s@`AO^c@h@SPi@b@o@d@o@d@}@d@q@ZcFtCk@P_@HYF[FWJSLg@`@QPSRQR[Te@VSLi@R[Bo@?WAU?WB[Jm@N]FaBd@{@ZmAd@a@VSJa@NWJUHg@ReAx@w@t@[ZW^OV_@dAc@fAg@|ACB[jA[dACJWbAAH]jBQ`AYtBW`Cs@|Fw@|Fw@|EeBxJa@`CUbBGd@K~@UxBOrAMlAOhCEfAErAAh@AjAAnB@~DFtDDtAHlCH|AFrAFhAHjAP~BRbCPjBVvBX~BR`BV|AZvB^~Bb@rC\\|B|@xFx@nFxApJlA`IpA~HlBtL\\zBz@tFX~BZvBt@rE|@fGv@fFHd@`@fCp@fE`@xCXbCXdCT~BJnANlBLrBN~CJlBFrBJ`DRfEXtGZpGTvELnBP`DLnBTfDLfBJzAR|BNhBFt@Dt@HbBJdCNxCVjFNrDHrCFzBBlBB|ABdB@dD@xA?lCCrDA|CIjJCjI?jEA`D@`E@~DBzEBhC@pBBnABvAFhBDnAHpAJnBTzCJpAHx@VhC^tCj@lDJj@Ll@RdAb@`B`@zAb@~A`@tAf@~AjBlFbB|EdA|CtAdEpAbE~@`DpAlEjBnGfA|DvBfI`CzJlAbFx@tDVnAb@|B^`C\\zBf@fDJx@Fh@JbATvBV~CLlBPzCJjCFxADjBBnADpB@hB@dDAfCCdDEpBIdEGfCKfCWtHU|F[tGa@~HU|DQhCWzDY~D_@nE[lDUzCM|A_@tES|BSrBMrAYzBYpBc@hCC\\APAP?X?F@R@\\"
                     },
                     "start_location" : {
                        "lat" : 54.60932889999999,
                        "lng" : -3.1407105
                     },
                     "travel_mode" : "DRIVING"
                  },
                  {
                     "distance" : {
                        "text" : "2.1 km",
                        "value" : 2119
                     },
                     "duration" : {
                        "text" : "2 mins",
                        "value" : 116
                     },
                     "end_location" : {
                        "lat" : 54.6660546,
                        "lng" : -3.3945179
                     },
                     "html_instructions" : "At \u003cb\u003eLamplugh Roundabout\u003c/b\u003e, take the \u003cb\u003e3rd\u003c/b\u003e exit and stay on \u003cb\u003eA66\u003c/b\u003e",
                     "maneuver" : "roundabout-left",
                     "polyline" : {
                        "points" : "ojqlIlrqSFBFFFHBJDL@H?H@HAJ?TCPCNENKLGFGBKBE?C?IJUR[Za@h@k@hA{@bBaAtBu@dBm@jAw@xA_AvA{@rA_CfDgCtD_AvAi@t@g@p@g@x@yBlDu@fAg@v@mApBmAnBuA`Cw@rAm@`AgBbD}@~A{@hBeBlDwAtCWd@m@pAwBbFaB~DoAbDk@|Ac@xA}@`De@`BK^Q`@MZ]n@ENKR[f@"
                     },
                     "start_location" : {
                        "lat" : 54.65271730000001,
                        "lng" : -3.3720695
                     },
                     "travel_mode" : "DRIVING"
                  },
                  {
                     "distance" : {
                        "text" : "5.7 km",
                        "value" : 5727
                     },
                     "duration" : {
                        "text" : "5 mins",
                        "value" : 276
                     },
                     "end_location" : {
                        "lat" : 54.6482483,
                        "lng" : -3.4718874
                     },
                     "html_instructions" : "At the roundabout, take the \u003cb\u003e1st\u003c/b\u003e exit and stay on \u003cb\u003eA66\u003c/b\u003e",
                     "maneuver" : "roundabout-left",
                     "polyline" : {
                        "points" : "y}slIv~uSAH?D?DADADABADABABBL?J?JCNE\\GTEb@AXKlAOhBS~A]zBQrAY|B[`DQfBY`DUbDKxAEr@GhAGhBCzAAn@AhA?bA@n@@d@@jADtAJ`CDx@JhBJfBFpAPxC\\lGNrCTdETjEnA`TFbATnDXjFJjBDv@PlDTpENrC@N\\nFBb@Fv@B\\B^JnAP|ANlAHj@P|@RfAXrAPv@\\jAXbAPj@Rf@Vp@Rf@Rd@Zl@r@rAh@z@p@~@n@v@j@j@x@t@\\Zl@d@hAt@z@j@x@h@|@|@\\b@h@v@`@x@b@bA`@hATv@T|@Pv@TtAFp@\\vCf@xEXbDj@nFd@pERxB`@fDVlC`@zD`@zDXfCV`CPjBNvALtAPhB^bDd@~Eb@vEVbCHjAHpALfBFnAN|CHnAJjBJnAJlAJjAX~BTdBRvAZlBd@~B^`BVdAVdAb@xAX~@^fAf@xA^~@Rf@\\v@n@pA\\n@\\p@z@vA`@l@\\d@h@r@h@p@bAlAd@j@\\^t@x@h@l@d@l@~@lAf@x@b@p@d@z@^r@Zv@`@`AXv@`@nAf@lBRz@\\bBP|@N~@Hf@FNHZRlB"
                     },
                     "start_location" : {
                        "lat" : 54.6660546,
                        "lng" : -3.3945179
                     },
                     "travel_mode" : "DRIVING"
                  },
                  {
                     "distance" : {
                        "text" : "4.6 km",
                        "value" : 4624
                     },
                     "duration" : {
                        "text" : "4 mins",
                        "value" : 221
                     },
                     "end_location" : {
                        "lat" : 54.6153458,
                        "lng" : -3.5135574
                     },
                     "html_instructions" : "At \u003cb\u003eBridgefoot Roundabout\u003c/b\u003e, take the \u003cb\u003e1st\u003c/b\u003e exit onto \u003cb\u003eA595\u003c/b\u003e",
                     "maneuver" : "roundabout-left",
                     "polyline" : {
                        "points" : "qnplIhbeTB?@@@@B@@@@@@B@B@B@B@Bn@@TBb@AhA@n@Db@Dv@HZHf@PZLZN`@Pl@`@h@\\b@^^ZVVRTNNPTb@n@TZZf@TZNXT`@P^Rb@N\\Vp@\\p@Zt@Vp@Xv@Vv@X|@Tr@ZhAdA`EV|@VbAT|@Z`AX|@X|@\\`AVn@Tl@`@dA\\t@Vh@Zr@@DR`@Xh@Zn@PZt@nAfAbBJNx@hAjAvAl@r@@BjApAtApArAnAxChCnAfAnB`Bf@d@^\\|ArAbBxAhBbBhHpGrDbDDDpE|DlAhAdAbAz@t@JJ`@b@z@|@z@~@`AbA~@dAdAnA|@fA|@hAt@`Ax@fAtBxCr@bAr@dA`BjCv@jAt@jAr@lAh@bAd@t@HPNVT^LTj@hAlA|Br@vAr@xAVf@zAtCx@vAXl@Vf@`AfBZl@Vf@DFn@nAt@vAHNp@lApAbC~@dBZj@\\p@dAnBbAlBbAlBlAbC`AhBbAjBz@~AT`@LLPJRN"
                     },
                     "start_location" : {
                        "lat" : 54.6482483,
                        "lng" : -3.4718874
                     },
                     "travel_mode" : "DRIVING"
                  },
                  {
                     "distance" : {
                        "text" : "1.0 km",
                        "value" : 1012
                     },
                     "duration" : {
                        "text" : "1 min",
                        "value" : 72
                     },
                     "end_location" : {
                        "lat" : 54.6089606,
                        "lng" : -3.5242608
                     },
                     "html_instructions" : "At the roundabout, take the \u003cb\u003e2nd\u003c/b\u003e exit and stay on \u003cb\u003eA595\u003c/b\u003e",
                     "maneuver" : "roundabout-left",
                     "polyline" : {
                        "points" : "}`jlIvfmTNIFAFAJBNLLRLZBV?XA^FVHf@H`@p@nA`AhBP\\l@fAHP`AbBJRz@~AtB|Dp@lAp@nAr@pAFLZf@`AjBt@vALVnAzBdAnBjAvBt@rAN\\LXJX@BHTJb@Nr@\\l@"
                     },
                     "start_location" : {
                        "lat" : 54.6153458,
                        "lng" : -3.5135574
                     },
                     "travel_mode" : "DRIVING"
                  },
                  {
                     "distance" : {
                        "text" : "0.8 km",
                        "value" : 815
                     },
                     "duration" : {
                        "text" : "1 min",
                        "value" : 55
                     },
                     "end_location" : {
                        "lat" : 54.60357399999999,
                        "lng" : -3.5326896
                     },
                     "html_instructions" : "At the roundabout, take the \u003cb\u003e1st\u003c/b\u003e exit and stay on \u003cb\u003eA595\u003c/b\u003e",
                     "maneuver" : "roundabout-left",
                     "polyline" : {
                        "points" : "_yhlIrioTBA@AB?B?B?B?B@@@B@BB@@BB@D@B@D@B@D?D@FfC|DdFjJjNlWHPhAtB`@dAn@zA"
                     },
                     "start_location" : {
                        "lat" : 54.6089606,
                        "lng" : -3.5242608
                     },
                     "travel_mode" : "DRIVING"
                  },
                  {
                     "distance" : {
                        "text" : "1.8 km",
                        "value" : 1785
                     },
                     "duration" : {
                        "text" : "2 mins",
                        "value" : 116
                     },
                     "end_location" : {
                        "lat" : 54.5888247,
                        "lng" : -3.5424295
                     },
                     "html_instructions" : "At the roundabout, take the \u003cb\u003e2nd\u003c/b\u003e exit onto \u003cb\u003eB5306\u003c/b\u003e",
                     "maneuver" : "roundabout-left",
                     "polyline" : {
                        "points" : "iwglIh~pT@?B?B?@@B?@@B@@?@B@?@@@@@@@@@B@@@B@D@B@D@D?D@D?Df@\\T\\T`@jAbBbAnAv@`At@v@PJb@V|@`@dAb@~@Z@@t@JjADh@H~@`@nAfAdBvA`Bt@zAX`B`@`B^dBl@bBv@rAz@rAx@dAbAp@l@PPbAlAx@|@TVfBtAj@R@?r@Lf@H\\DD@j@Jl@Ll@Lj@Hj@LZDZJj@Z`@Vf@X`@X`@\\\\\\\\^j@n@"
                     },
                     "start_location" : {
                        "lat" : 54.60357399999999,
                        "lng" : -3.5326896
                     },
                     "travel_mode" : "DRIVING"
                  },
                  {
                     "distance" : {
                        "text" : "1.4 km",
                        "value" : 1409
                     },
                     "duration" : {
                        "text" : "2 mins",
                        "value" : 103
                     },
                     "end_location" : {
                        "lat" : 54.5779416,
                        "lng" : -3.5434474
                     },
                     "html_instructions" : "Turn \u003cb\u003eleft\u003c/b\u003e",
                     "maneuver" : "turn-left",
                     "polyline" : {
                        "points" : "c{dlId{rTd@aAh@gA@Ej@kAb@aAd@eAf@gAh@gAd@w@h@}@b@u@`@m@`@a@d@c@f@[\\M^MV?XLPNJJd@^XRHD@@\\RnAb@h@NVH\\L`@NZNVRZXT\\Rl@d@`BZ`ARd@`@l@XTZLb@Dh@JXJZH\\D^@^@ZH\\R\\V`@b@^T\\Vd@b@j@l@l@l@`@`@b@Zb@P\\HZ?j@Gp@Ar@D\\J"
                     },
                     "start_location" : {
                        "lat" : 54.5888247,
                        "lng" : -3.5424295
                     },
                     "travel_mode" : "DRIVING"
                  },
                  {
                     "distance" : {
                        "text" : "1.9 km",
                        "value" : 1902
                     },
                     "duration" : {
                        "text" : "2 mins",
                        "value" : 121
                     },
                     "end_location" : {
                        "lat" : 54.5620819,
                        "lng" : -3.5515351
                     },
                     "html_instructions" : "Slight \u003cb\u003eright\u003c/b\u003e",
                     "maneuver" : "turn-slight-right",
                     "polyline" : {
                        "points" : "cwblIpasTXZNHBF`@f@d@h@RNh@^h@Zh@^j@b@`A|@rApAf@h@^Zd@Vn@`@j@Xb@P^Hd@@hA@`B@H?bA?nA?bA@x@Hb@Nf@XTRLJHHRRJLLPT\\dBnC@B?@?BA@MPA@?B?B?B?DBFBFTZNTRVHFHFFBJDJBNDn@Fh@F`@HzBn@nA^nAh@VLlBhAbAb@nAh@jCv@rBh@`C`@|BZ`ANj@FxAHhCF"
                     },
                     "start_location" : {
                        "lat" : 54.5779416,
                        "lng" : -3.5434474
                     },
                     "travel_mode" : "DRIVING"
                  },
                  {
                     "distance" : {
                        "text" : "0.2 km",
                        "value" : 154
                     },
                     "duration" : {
                        "text" : "1 min",
                        "value" : 19
                     },
                     "end_location" : {
                        "lat" : 54.5607002,
                        "lng" : -3.551531
                     },
                     "html_instructions" : "Continue onto \u003cb\u003eMoresby Parks Rd\u003c/b\u003e",
                     "polyline" : {
                        "points" : "_t_lIbttTtCAjAAF?h@@"
                     },
                     "start_location" : {
                        "lat" : 54.5620819,
                        "lng" : -3.5515351
                     },
                     "travel_mode" : "DRIVING"
                  },
                  {
                     "distance" : {
                        "text" : "80 m",
                        "value" : 80
                     },
                     "duration" : {
                        "text" : "1 min",
                        "value" : 15
                     },
                     "end_location" : {
                        "lat" : 54.5605154,
                        "lng" : -3.5527034
                     },
                     "html_instructions" : "Turn \u003cb\u003eright\u003c/b\u003e onto \u003cb\u003eParkfields Rd\u003c/b\u003e",
                     "maneuver" : "turn-right",
                     "polyline" : {
                        "points" : "kk_lI`ttTAn@@P?J@NBRF\\F`@Lv@"
                     },
                     "start_location" : {
                        "lat" : 54.5607002,
                        "lng" : -3.551531
                     },
                     "travel_mode" : "DRIVING"
                  },
                  {
                     "distance" : {
                        "text" : "93 m",
                        "value" : 93
                     },
                     "duration" : {
                        "text" : "1 min",
                        "value" : 18
                     },
                     "end_location" : {
                        "lat" : 54.5597613,
                        "lng" : -3.5521997
                     },
                     "html_instructions" : "Turn \u003cb\u003eleft\u003c/b\u003e onto \u003cb\u003eRowntree Cres\u003c/b\u003e\u003cdiv style=\"font-size:0.9em\"\u003eDestination will be on the left\u003c/div\u003e",
                     "maneuver" : "turn-left",
                     "polyline" : {
                        "points" : "gj_lIj{tTv@MZCBAJGDABCBC`@u@BG"
                     },
                     "start_location" : {
                        "lat" : 54.5605154,
                        "lng" : -3.5527034
                     },
                     "travel_mode" : "DRIVING"
                  }
               ],
               "traffic_speed_entry" : [],
               "via_waypoint" : []
            }
         ],
         "overview_polyline" : {
            "points" : "}`{~HdqeHdF_x@_`@z{@`Srz@qN|u@as@xsDuIn|AcZpSuZ`bBgaAjaHo[j|GzEb_Dv@`VqLiJsr@f@swBfH}x@eAw}Ado@{eAlj@i|EpYsqB|xDga@xlAmm@j]m]|x@ipAx}@a}A`CukBdc@_u@z^er@||Ail@`fC}NrdCvTldC}f@dkBkb@vqCdK`nBaf@~wHmc@zeC|IdaCr`@leB_DzqAyaAfxBamAbdBy{@|DcuAeSycByLyvBjFa}Avj@mpAv~@ww@dwAag@jbBoi@zb@yqAbKq{@mUw^qc@ia@sDu{@dbAwyBdq@ytBxMs|AbaBwaBjhAusA`yAubB`r@izDhv@}p@fX_[tpAma@fcB}_@fbFiRraCsz@lpAa`@lG}\\mVeu@oVkdAzl@a|DpSs~CrbAigDkq@iwBrDmjAdk@s}Bj_B_iCrrCc~@``@weBjOgqBb}@gxC~H}xCyi@seCvnAotBdhIszAx{Ds~AfeB{cArOqhAcWukB|TkmBp|DofCdcForAzaCsx@lbAmt@hiCw{@dy@gcA|yAsdAbXsx@pfA_YzfB{Pzd@cl@d^clA`DulAzEekApQuiDgq@krEgo@muBlf@kyBkF}aEmsA_cByJ_p@_hAyhAklAcf@sV{\\vHkf@~Dyj@{g@ql@aj@ki@sFwp@lWmeAfdAaxBdlGydAp{AqpAhz@uzBj_AueBnrAk_D|O}tB|s@u}Bh`@}aBiVqj@iUae@|MebBbpBo}@dy@i{@AsrDvLm}Asv@eaAws@{k@Sst@nc@o_A]yoB}XioBgTsyAyr@gaBqvAmzD_Wi{BulAuoCkLcfAoMar@}A{h@ui@_Xk|@}a@qg@_j@gd@_~@ej@}cDafDojCgmB_dCmdC{v@{Pyg@jSg]iHkYmw@ek@ixBq~@ed@qf@_Bi_@zp@eiA~sAazA{RcpArAakAse@yn@xa@oq@nxAiz@p}@{aA`y@_eA|]kqAp_@}`Bpx@qc@h]qkAtHowBtmAytAh|A}_CrsAqdBtc@gsBxyAsnAxj@in@hw@ew@pfCzVjoCmEfpBnWtyD`m@nzHFt`CqYpfBnh@b~GjNrgItw@~qC~q@nkBt]l~AXvaBdZjzAy@xzAoU`vD~^zbBhXxxAgMlx@u\\vOubBviAs~AnmAa|@dg@awAt}@i]jxAlXnvCd]tkHxs@lzCyDhxC_cA|aCwTrn@kCbbBxQboBxd@`yA~T~lBjc@f|@jo@bbAr{BnpCfgApsBnt@tiAr{@ba@ra@oOpbArp@`vAda@|DtA"
         },
         "summary" : "M6",
         "warnings" : [],
         "waypoint_order" : []
      }
   ],
   "status" : "OK"
}